{
  "array": [
  {
    "image": "ILSVRC2012_val_00001163.JPEG",
    "wnid": "n01818515",
    "true_label": "macaw",
    "predicted_index": 88,
    "predicted_label": "macaw",
    "correct": true
  },
  {
    "image": "ILSVRC2012_val_00003743.JPEG",
    "wnid": "n01818515",
    "true_label": "macaw",
    "predicted_index": 88,
    "predicted_label": "macaw",
    "correct": true
  },
  {
    "image": "ILSVRC2012_val_00003823.JPEG",
    "wnid": "n01818515",
    "true_label": "macaw",
    "predicted_index": 88,
    "predicted_label": "macaw",
    "correct": true
  },
  {
    "image": "ILSVRC2012_val_00003987.JPEG",
    "wnid": "n01818515",
    "true_label": "macaw",
    "predicted_index": 88,
    "predicted_label": "macaw",
    "correct": true
  },
  {
    "image": "ILSVRC2012_val_00004944.JPEG",
    "wnid": "n01818515",
    "true_label": "macaw",
    "predicted_index": 88,
    "predicted_label": "macaw",
    "correct": true
  },
  {
    "image": "ILSVRC2012_val_00007081.JPEG",
    "wnid": "n01818515",
    "true_label": "macaw",
    "predicted_index": 88,
    "predicted_label": "macaw",
    "correct": true
  },
  {
    "image": "ILSVRC2012_val_00007156.JPEG",
    "wnid": "n01818515",
    "true_label": "macaw",
    "predicted_index": 397,
    "predicted_label": "puffer",
    "correct": false
  },
  {
    "image": "ILSVRC2012_val_00007168.JPEG",
    "wnid": "n01818515",
    "true_label": "macaw",
    "predicted_index": 88,
    "predicted_label": "macaw",
    "correct": true
  },
  {
    "image": "ILSVRC2012_val_00007474.JPEG",
    "wnid": "n01818515",
    "true_label": "macaw",
    "predicted_index": 903,
    "predicted_label": "wig",
    "correct": false
  },
  {
    "image": "ILSVRC2012_val_00007576.JPEG",
    "wnid": "n01818515",
    "true_label": "macaw",
    "predicted_index": 88,
    "predicted_label": "macaw",
    "correct": true
  },
  {
    "image": "ILSVRC2012_val_00009091.JPEG",
    "wnid": "n01818515",
    "true_label": "macaw",
    "predicted_index": 88,
    "predicted_label": "macaw",
    "correct": true
  },
  {
    "image": "ILSVRC2012_val_00009146.JPEG",
    "wnid": "n01818515",
    "true_label": "macaw",
    "predicted_index": 88,
    "predicted_label": "macaw",
    "correct": true
  },
  {
    "image": "ILSVRC2012_val_00009811.JPEG",
    "wnid": "n01818515",
    "true_label": "macaw",
    "predicted_index": 88,
    "predicted_label": "macaw",
    "correct": true
  },
  {
    "image": "ILSVRC2012_val_00009857.JPEG",
    "wnid": "n01818515",
    "true_label": "macaw",
    "predicted_index": 88,
    "predicted_label": "macaw",
    "correct": true
  },
  {
    "image": "ILSVRC2012_val_00010477.JPEG",
    "wnid": "n01818515",
    "true_label": "macaw",
    "predicted_index": 88,
    "predicted_label": "macaw",
    "correct": true
  },
  {
    "image": "ILSVRC2012_val_00012586.JPEG",
    "wnid": "n01818515",
    "true_label": "macaw",
    "predicted_index": 88,
    "predicted_label": "macaw",
    "correct": true
  },
  {
    "image": "ILSVRC2012_val_00012864.JPEG",
    "wnid": "n01818515",
    "true_label": "macaw",
    "predicted_index": 88,
    "predicted_label": "macaw",
    "correct": true
  },
  {
    "image": "ILSVRC2012_val_00013768.JPEG",
    "wnid": "n01818515",
    "true_label": "macaw",
    "predicted_index": 88,
    "predicted_label": "macaw",
    "correct": true
  },
  {
    "image": "ILSVRC2012_val_00017029.JPEG",
    "wnid": "n01818515",
    "true_label": "macaw",
    "predicted_index": 88,
    "predicted_label": "macaw",
    "correct": true
  },
  {
    "image": "ILSVRC2012_val_00018993.JPEG",
    "wnid": "n01818515",
    "true_label": "macaw",
    "predicted_index": 88,
    "predicted_label": "macaw",
    "correct": true
  },
  {
    "image": "ILSVRC2012_val_00021663.JPEG",
    "wnid": "n01818515",
    "true_label": "macaw",
    "predicted_index": 21,
    "predicted_label": "kite",
    "correct": false
  },
  {
    "image": "ILSVRC2012_val_00022355.JPEG",
    "wnid": "n01818515",
    "true_label": "macaw",
    "predicted_index": 88,
    "predicted_label": "macaw",
    "correct": true
  },
  {
    "image": "ILSVRC2012_val_00022745.JPEG",
    "wnid": "n01818515",
    "true_label": "macaw",
    "predicted_index": 88,
    "predicted_label": "macaw",
    "correct": true
  },
  {
    "image": "ILSVRC2012_val_00024381.JPEG",
    "wnid": "n01818515",
    "true_label": "macaw",
    "predicted_index": 88,
    "predicted_label": "macaw",
    "correct": true
  },
  {
    "image": "ILSVRC2012_val_00025872.JPEG",
    "wnid": "n01818515",
    "true_label": "macaw",
    "predicted_index": 88,
    "predicted_label": "macaw",
    "correct": true
  },
  {
    "image": "ILSVRC2012_val_00026141.JPEG",
    "wnid": "n01818515",
    "true_label": "macaw",
    "predicted_index": 88,
    "predicted_label": "macaw",
    "correct": true
  },
  {
    "image": "ILSVRC2012_val_00027656.JPEG",
    "wnid": "n01818515",
    "true_label": "macaw",
    "predicted_index": 88,
    "predicted_label": "macaw",
    "correct": true
  },
  {
    "image": "ILSVRC2012_val_00029210.JPEG",
    "wnid": "n01818515",
    "true_label": "macaw",
    "predicted_index": 88,
    "predicted_label": "macaw",
    "correct": true
  },
  {
    "image": "ILSVRC2012_val_00029991.JPEG",
    "wnid": "n01818515",
    "true_label": "macaw",
    "predicted_index": 88,
    "predicted_label": "macaw",
    "correct": true
  },
  {
    "image": "ILSVRC2012_val_00030148.JPEG",
    "wnid": "n01818515",
    "true_label": "macaw",
    "predicted_index": 88,
    "predicted_label": "macaw",
    "correct": true
  },
  {
    "image": "ILSVRC2012_val_00030397.JPEG",
    "wnid": "n01818515",
    "true_label": "macaw",
    "predicted_index": 88,
    "predicted_label": "macaw",
    "correct": true
  },
  {
    "image": "ILSVRC2012_val_00031392.JPEG",
    "wnid": "n01818515",
    "true_label": "macaw",
    "predicted_index": 88,
    "predicted_label": "macaw",
    "correct": true
  },
  {
    "image": "ILSVRC2012_val_00032473.JPEG",
    "wnid": "n01818515",
    "true_label": "macaw",
    "predicted_index": 88,
    "predicted_label": "macaw",
    "correct": true
  },
  {
    "image": "ILSVRC2012_val_00033078.JPEG",
    "wnid": "n01818515",
    "true_label": "macaw",
    "predicted_index": 88,
    "predicted_label": "macaw",
    "correct": true
  },
  {
    "image": "ILSVRC2012_val_00034347.JPEG",
    "wnid": "n01818515",
    "true_label": "macaw",
    "predicted_index": 88,
    "predicted_label": "macaw",
    "correct": true
  },
  {
    "image": "ILSVRC2012_val_00036361.JPEG",
    "wnid": "n01818515",
    "true_label": "macaw",
    "predicted_index": 88,
    "predicted_label": "macaw",
    "correct": true
  },
  {
    "image": "ILSVRC2012_val_00036744.JPEG",
    "wnid": "n01818515",
    "true_label": "macaw",
    "predicted_index": 88,
    "predicted_label": "macaw",
    "correct": true
  },
  {
    "image": "ILSVRC2012_val_00036879.JPEG",
    "wnid": "n01818515",
    "true_label": "macaw",
    "predicted_index": 88,
    "predicted_label": "macaw",
    "correct": true
  },
  {
    "image": "ILSVRC2012_val_00037188.JPEG",
    "wnid": "n01818515",
    "true_label": "macaw",
    "predicted_index": 88,
    "predicted_label": "macaw",
    "correct": true
  },
  {
    "image": "ILSVRC2012_val_00040183.JPEG",
    "wnid": "n01818515",
    "true_label": "macaw",
    "predicted_index": 88,
    "predicted_label": "macaw",
    "correct": true
  },
  {
    "image": "ILSVRC2012_val_00040359.JPEG",
    "wnid": "n01818515",
    "true_label": "macaw",
    "predicted_index": 88,
    "predicted_label": "macaw",
    "correct": true
  },
  {
    "image": "ILSVRC2012_val_00041556.JPEG",
    "wnid": "n01818515",
    "true_label": "macaw",
    "predicted_index": 88,
    "predicted_label": "macaw",
    "correct": true
  },
  {
    "image": "ILSVRC2012_val_00042071.JPEG",
    "wnid": "n01818515",
    "true_label": "macaw",
    "predicted_index": 88,
    "predicted_label": "macaw",
    "correct": true
  },
  {
    "image": "ILSVRC2012_val_00043794.JPEG",
    "wnid": "n01818515",
    "true_label": "macaw",
    "predicted_index": 88,
    "predicted_label": "macaw",
    "correct": true
  },
  {
    "image": "ILSVRC2012_val_00046534.JPEG",
    "wnid": "n01818515",
    "true_label": "macaw",
    "predicted_index": 88,
    "predicted_label": "macaw",
    "correct": true
  },
  {
    "image": "ILSVRC2012_val_00047547.JPEG",
    "wnid": "n01818515",
    "true_label": "macaw",
    "predicted_index": 88,
    "predicted_label": "macaw",
    "correct": true
  },
  {
    "image": "ILSVRC2012_val_00047587.JPEG",
    "wnid": "n01818515",
    "true_label": "macaw",
    "predicted_index": 88,
    "predicted_label": "macaw",
    "correct": true
  },
  {
    "image": "ILSVRC2012_val_00047696.JPEG",
    "wnid": "n01818515",
    "true_label": "macaw",
    "predicted_index": 88,
    "predicted_label": "macaw",
    "correct": true
  },
  {
    "image": "ILSVRC2012_val_00048027.JPEG",
    "wnid": "n01818515",
    "true_label": "macaw",
    "predicted_index": 88,
    "predicted_label": "macaw",
    "correct": true
  },
  {
    "image": "ILSVRC2012_val_00048265.JPEG",
    "wnid": "n01818515",
    "true_label": "macaw",
    "predicted_index": 88,
    "predicted_label": "macaw",
    "correct": true
  },
  {
    "image": "ILSVRC2012_val_00000952.JPEG",
    "wnid": "n01843383",
    "true_label": "toucan",
    "predicted_index": 96,
    "predicted_label": "toucan",
    "correct": true
  },
  {
    "image": "ILSVRC2012_val_00001158.JPEG",
    "wnid": "n01843383",
    "true_label": "toucan",
    "predicted_index": 92,
    "predicted_label": "bee eater",
    "correct": false
  },
  {
    "image": "ILSVRC2012_val_00003271.JPEG",
    "wnid": "n01843383",
    "true_label": "toucan",
    "predicted_index": 96,
    "predicted_label": "toucan",
    "correct": true
  },
  {
    "image": "ILSVRC2012_val_00005901.JPEG",
    "wnid": "n01843383",
    "true_label": "toucan",
    "predicted_index": 96,
    "predicted_label": "toucan",
    "correct": true
  },
  {
    "image": "ILSVRC2012_val_00006460.JPEG",
    "wnid": "n01843383",
    "true_label": "toucan",
    "predicted_index": 96,
    "predicted_label": "toucan",
    "correct": true
  },
  {
    "image": "ILSVRC2012_val_00008549.JPEG",
    "wnid": "n01843383",
    "true_label": "toucan",
    "predicted_index": 96,
    "predicted_label": "toucan",
    "correct": true
  },
  {
    "image": "ILSVRC2012_val_00009145.JPEG",
    "wnid": "n01843383",
    "true_label": "toucan",
    "predicted_index": 96,
    "predicted_label": "toucan",
    "correct": true
  },
  {
    "image": "ILSVRC2012_val_00009974.JPEG",
    "wnid": "n01843383",
    "true_label": "toucan",
    "predicted_index": 93,
    "predicted_label": "hornbill",
    "correct": false
  },
  {
    "image": "ILSVRC2012_val_00011011.JPEG",
    "wnid": "n01843383",
    "true_label": "toucan",
    "predicted_index": 96,
    "predicted_label": "toucan",
    "correct": true
  },
  {
    "image": "ILSVRC2012_val_00011375.JPEG",
    "wnid": "n01843383",
    "true_label": "toucan",
    "predicted_index": 96,
    "predicted_label": "toucan",
    "correct": true
  },
  {
    "image": "ILSVRC2012_val_00012601.JPEG",
    "wnid": "n01843383",
    "true_label": "toucan",
    "predicted_index": 96,
    "predicted_label": "toucan",
    "correct": true
  },
  {
    "image": "ILSVRC2012_val_00014068.JPEG",
    "wnid": "n01843383",
    "true_label": "toucan",
    "predicted_index": 96,
    "predicted_label": "toucan",
    "correct": true
  },
  {
    "image": "ILSVRC2012_val_00015298.JPEG",
    "wnid": "n01843383",
    "true_label": "toucan",
    "predicted_index": 96,
    "predicted_label": "toucan",
    "correct": true
  },
  {
    "image": "ILSVRC2012_val_00015673.JPEG",
    "wnid": "n01843383",
    "true_label": "toucan",
    "predicted_index": 96,
    "predicted_label": "toucan",
    "correct": true
  },
  {
    "image": "ILSVRC2012_val_00018463.JPEG",
    "wnid": "n01843383",
    "true_label": "toucan",
    "predicted_index": 96,
    "predicted_label": "toucan",
    "correct": true
  },
  {
    "image": "ILSVRC2012_val_00018780.JPEG",
    "wnid": "n01843383",
    "true_label": "toucan",
    "predicted_index": 96,
    "predicted_label": "toucan",
    "correct": true
  },
  {
    "image": "ILSVRC2012_val_00019884.JPEG",
    "wnid": "n01843383",
    "true_label": "toucan",
    "predicted_index": 96,
    "predicted_label": "toucan",
    "correct": true
  },
  {
    "image": "ILSVRC2012_val_00020749.JPEG",
    "wnid": "n01843383",
    "true_label": "toucan",
    "predicted_index": 96,
    "predicted_label": "toucan",
    "correct": true
  },
  {
    "image": "ILSVRC2012_val_00020909.JPEG",
    "wnid": "n01843383",
    "true_label": "toucan",
    "predicted_index": 96,
    "predicted_label": "toucan",
    "correct": true
  },
  {
    "image": "ILSVRC2012_val_00023371.JPEG",
    "wnid": "n01843383",
    "true_label": "toucan",
    "predicted_index": 96,
    "predicted_label": "toucan",
    "correct": true
  },
  {
    "image": "ILSVRC2012_val_00023390.JPEG",
    "wnid": "n01843383",
    "true_label": "toucan",
    "predicted_index": 96,
    "predicted_label": "toucan",
    "correct": true
  },
  {
    "image": "ILSVRC2012_val_00024063.JPEG",
    "wnid": "n01843383",
    "true_label": "toucan",
    "predicted_index": 96,
    "predicted_label": "toucan",
    "correct": true
  },
  {
    "image": "ILSVRC2012_val_00024423.JPEG",
    "wnid": "n01843383",
    "true_label": "toucan",
    "predicted_index": 96,
    "predicted_label": "toucan",
    "correct": true
  },
  {
    "image": "ILSVRC2012_val_00024525.JPEG",
    "wnid": "n01843383",
    "true_label": "toucan",
    "predicted_index": 96,
    "predicted_label": "toucan",
    "correct": true
  },
  {
    "image": "ILSVRC2012_val_00024848.JPEG",
    "wnid": "n01843383",
    "true_label": "toucan",
    "predicted_index": 96,
    "predicted_label": "toucan",
    "correct": true
  },
  {
    "image": "ILSVRC2012_val_00025371.JPEG",
    "wnid": "n01843383",
    "true_label": "toucan",
    "predicted_index": 90,
    "predicted_label": "lorikeet",
    "correct": false
  },
  {
    "image": "ILSVRC2012_val_00025631.JPEG",
    "wnid": "n01843383",
    "true_label": "toucan",
    "predicted_index": 96,
    "predicted_label": "toucan",
    "correct": true
  },
  {
    "image": "ILSVRC2012_val_00025785.JPEG",
    "wnid": "n01843383",
    "true_label": "toucan",
    "predicted_index": 96,
    "predicted_label": "toucan",
    "correct": true
  },
  {
    "image": "ILSVRC2012_val_00027602.JPEG",
    "wnid": "n01843383",
    "true_label": "toucan",
    "predicted_index": 96,
    "predicted_label": "toucan",
    "correct": true
  },
  {
    "image": "ILSVRC2012_val_00029589.JPEG",
    "wnid": "n01843383",
    "true_label": "toucan",
    "predicted_index": 387,
    "predicted_label": "lesser panda",
    "correct": false
  },
  {
    "image": "ILSVRC2012_val_00029948.JPEG",
    "wnid": "n01843383",
    "true_label": "toucan",
    "predicted_index": 96,
    "predicted_label": "toucan",
    "correct": true
  },
  {
    "image": "ILSVRC2012_val_00030000.JPEG",
    "wnid": "n01843383",
    "true_label": "toucan",
    "predicted_index": 96,
    "predicted_label": "toucan",
    "correct": true
  },
  {
    "image": "ILSVRC2012_val_00030629.JPEG",
    "wnid": "n01843383",
    "true_label": "toucan",
    "predicted_index": 96,
    "predicted_label": "toucan",
    "correct": true
  },
  {
    "image": "ILSVRC2012_val_00030702.JPEG",
    "wnid": "n01843383",
    "true_label": "toucan",
    "predicted_index": 96,
    "predicted_label": "toucan",
    "correct": true
  },
  {
    "image": "ILSVRC2012_val_00031298.JPEG",
    "wnid": "n01843383",
    "true_label": "toucan",
    "predicted_index": 96,
    "predicted_label": "toucan",
    "correct": true
  },
  {
    "image": "ILSVRC2012_val_00032122.JPEG",
    "wnid": "n01843383",
    "true_label": "toucan",
    "predicted_index": 752,
    "predicted_label": "racket",
    "correct": false
  },
  {
    "image": "ILSVRC2012_val_00032158.JPEG",
    "wnid": "n01843383",
    "true_label": "toucan",
    "predicted_index": 393,
    "predicted_label": "anemone fish",
    "correct": false
  },
  {
    "image": "ILSVRC2012_val_00032492.JPEG",
    "wnid": "n01843383",
    "true_label": "toucan",
    "predicted_index": 96,
    "predicted_label": "toucan",
    "correct": true
  },
  {
    "image": "ILSVRC2012_val_00034194.JPEG",
    "wnid": "n01843383",
    "true_label": "toucan",
    "predicted_index": 96,
    "predicted_label": "toucan",
    "correct": true
  },
  {
    "image": "ILSVRC2012_val_00035274.JPEG",
    "wnid": "n01843383",
    "true_label": "toucan",
    "predicted_index": 96,
    "predicted_label": "toucan",
    "correct": true
  },
  {
    "image": "ILSVRC2012_val_00036354.JPEG",
    "wnid": "n01843383",
    "true_label": "toucan",
    "predicted_index": 96,
    "predicted_label": "toucan",
    "correct": true
  },
  {
    "image": "ILSVRC2012_val_00037244.JPEG",
    "wnid": "n01843383",
    "true_label": "toucan",
    "predicted_index": 96,
    "predicted_label": "toucan",
    "correct": true
  },
  {
    "image": "ILSVRC2012_val_00038685.JPEG",
    "wnid": "n01843383",
    "true_label": "toucan",
    "predicted_index": 1,
    "predicted_label": "goldfish",
    "correct": false
  },
  {
    "image": "ILSVRC2012_val_00040051.JPEG",
    "wnid": "n01843383",
    "true_label": "toucan",
    "predicted_index": 93,
    "predicted_label": "hornbill",
    "correct": false
  },
  {
    "image": "ILSVRC2012_val_00043509.JPEG",
    "wnid": "n01843383",
    "true_label": "toucan",
    "predicted_index": 96,
    "predicted_label": "toucan",
    "correct": true
  },
  {
    "image": "ILSVRC2012_val_00046438.JPEG",
    "wnid": "n01843383",
    "true_label": "toucan",
    "predicted_index": 96,
    "predicted_label": "toucan",
    "correct": true
  },
  {
    "image": "ILSVRC2012_val_00046755.JPEG",
    "wnid": "n01843383",
    "true_label": "toucan",
    "predicted_index": 96,
    "predicted_label": "toucan",
    "correct": true
  },
  {
    "image": "ILSVRC2012_val_00048203.JPEG",
    "wnid": "n01843383",
    "true_label": "toucan",
    "predicted_index": 96,
    "predicted_label": "toucan",
    "correct": true
  },
  {
    "image": "ILSVRC2012_val_00049093.JPEG",
    "wnid": "n01843383",
    "true_label": "toucan",
    "predicted_index": 96,
    "predicted_label": "toucan",
    "correct": true
  },
  {
    "image": "ILSVRC2012_val_00049553.JPEG",
    "wnid": "n01843383",
    "true_label": "toucan",
    "predicted_index": 96,
    "predicted_label": "toucan",
    "correct": true
  },
  {
    "image": "ILSVRC2012_val_00000207.JPEG",
    "wnid": "n02058221",
    "true_label": "albatross",
    "predicted_index": 82,
    "predicted_label": "ruffed grouse",
    "correct": false
  },
  {
    "image": "ILSVRC2012_val_00000492.JPEG",
    "wnid": "n02058221",
    "true_label": "albatross",
    "predicted_index": 22,
    "predicted_label": "bald eagle",
    "correct": false
  },
  {
    "image": "ILSVRC2012_val_00002090.JPEG",
    "wnid": "n02058221",
    "true_label": "albatross",
    "predicted_index": 146,
    "predicted_label": "albatross",
    "correct": true
  },
  {
    "image": "ILSVRC2012_val_00003410.JPEG",
    "wnid": "n02058221",
    "true_label": "albatross",
    "predicted_index": 146,
    "predicted_label": "albatross",
    "correct": true
  },
  {
    "image": "ILSVRC2012_val_00003845.JPEG",
    "wnid": "n02058221",
    "true_label": "albatross",
    "predicted_index": 146,
    "predicted_label": "albatross",
    "correct": true
  },
  {
    "image": "ILSVRC2012_val_00005030.JPEG",
    "wnid": "n02058221",
    "true_label": "albatross",
    "predicted_index": 146,
    "predicted_label": "albatross",
    "correct": true
  },
  {
    "image": "ILSVRC2012_val_00005890.JPEG",
    "wnid": "n02058221",
    "true_label": "albatross",
    "predicted_index": 146,
    "predicted_label": "albatross",
    "correct": true
  },
  {
    "image": "ILSVRC2012_val_00005988.JPEG",
    "wnid": "n02058221",
    "true_label": "albatross",
    "predicted_index": 146,
    "predicted_label": "albatross",
    "correct": true
  },
  {
    "image": "ILSVRC2012_val_00007276.JPEG",
    "wnid": "n02058221",
    "true_label": "albatross",
    "predicted_index": 145,
    "predicted_label": "king penguin",
    "correct": false
  },
  {
    "image": "ILSVRC2012_val_00008056.JPEG",
    "wnid": "n02058221",
    "true_label": "albatross",
    "predicted_index": 145,
    "predicted_label": "king penguin",
    "correct": false
  },
  {
    "image": "ILSVRC2012_val_00008106.JPEG",
    "wnid": "n02058221",
    "true_label": "albatross",
    "predicted_index": 146,
    "predicted_label": "albatross",
    "correct": true
  },
  {
    "image": "ILSVRC2012_val_00009694.JPEG",
    "wnid": "n02058221",
    "true_label": "albatross",
    "predicted_index": 146,
    "predicted_label": "albatross",
    "correct": true
  },
  {
    "image": "ILSVRC2012_val_00009908.JPEG",
    "wnid": "n02058221",
    "true_label": "albatross",
    "predicted_index": 146,
    "predicted_label": "albatross",
    "correct": true
  },
  {
    "image": "ILSVRC2012_val_00010399.JPEG",
    "wnid": "n02058221",
    "true_label": "albatross",
    "predicted_index": 146,
    "predicted_label": "albatross",
    "correct": true
  },
  {
    "image": "ILSVRC2012_val_00010446.JPEG",
    "wnid": "n02058221",
    "true_label": "albatross",
    "predicted_index": 2,
    "predicted_label": "great white shark",
    "correct": false
  },
  {
    "image": "ILSVRC2012_val_00012187.JPEG",
    "wnid": "n02058221",
    "true_label": "albatross",
    "predicted_index": 146,
    "predicted_label": "albatross",
    "correct": true
  },
  {
    "image": "ILSVRC2012_val_00013901.JPEG",
    "wnid": "n02058221",
    "true_label": "albatross",
    "predicted_index": 146,
    "predicted_label": "albatross",
    "correct": true
  },
  {
    "image": "ILSVRC2012_val_00015132.JPEG",
    "wnid": "n02058221",
    "true_label": "albatross",
    "predicted_index": 146,
    "predicted_label": "albatross",
    "correct": true
  },
  {
    "image": "ILSVRC2012_val_00016571.JPEG",
    "wnid": "n02058221",
    "true_label": "albatross",
    "predicted_index": 89,
    "predicted_label": "sulphur-crested cockatoo",
    "correct": false
  },
  {
    "image": "ILSVRC2012_val_00017197.JPEG",
    "wnid": "n02058221",
    "true_label": "albatross",
    "predicted_index": 146,
    "predicted_label": "albatross",
    "correct": true
  },
  {
    "image": "ILSVRC2012_val_00017807.JPEG",
    "wnid": "n02058221",
    "true_label": "albatross",
    "predicted_index": 146,
    "predicted_label": "albatross",
    "correct": true
  },
  {
    "image": "ILSVRC2012_val_00018662.JPEG",
    "wnid": "n02058221",
    "true_label": "albatross",
    "predicted_index": 146,
    "predicted_label": "albatross",
    "correct": true
  },
  {
    "image": "ILSVRC2012_val_00018871.JPEG",
    "wnid": "n02058221",
    "true_label": "albatross",
    "predicted_index": 146,
    "predicted_label": "albatross",
    "correct": true
  },
  {
    "image": "ILSVRC2012_val_00022688.JPEG",
    "wnid": "n02058221",
    "true_label": "albatross",
    "predicted_index": 146,
    "predicted_label": "albatross",
    "correct": true
  },
  {
    "image": "ILSVRC2012_val_00022938.JPEG",
    "wnid": "n02058221",
    "true_label": "albatross",
    "predicted_index": 146,
    "predicted_label": "albatross",
    "correct": true
  },
  {
    "image": "ILSVRC2012_val_00026683.JPEG",
    "wnid": "n02058221",
    "true_label": "albatross",
    "predicted_index": 146,
    "predicted_label": "albatross",
    "correct": true
  },
  {
    "image": "ILSVRC2012_val_00026716.JPEG",
    "wnid": "n02058221",
    "true_label": "albatross",
    "predicted_index": 146,
    "predicted_label": "albatross",
    "correct": true
  },
  {
    "image": "ILSVRC2012_val_00026733.JPEG",
    "wnid": "n02058221",
    "true_label": "albatross",
    "predicted_index": 146,
    "predicted_label": "albatross",
    "correct": true
  },
  {
    "image": "ILSVRC2012_val_00026758.JPEG",
    "wnid": "n02058221",
    "true_label": "albatross",
    "predicted_index": 146,
    "predicted_label": "albatross",
    "correct": true
  },
  {
    "image": "ILSVRC2012_val_00026949.JPEG",
    "wnid": "n02058221",
    "true_label": "albatross",
    "predicted_index": 146,
    "predicted_label": "albatross",
    "correct": true
  },
  {
    "image": "ILSVRC2012_val_00029223.JPEG",
    "wnid": "n02058221",
    "true_label": "albatross",
    "predicted_index": 146,
    "predicted_label": "albatross",
    "correct": true
  },
  {
    "image": "ILSVRC2012_val_00031023.JPEG",
    "wnid": "n02058221",
    "true_label": "albatross",
    "predicted_index": 146,
    "predicted_label": "albatross",
    "correct": true
  },
  {
    "image": "ILSVRC2012_val_00032575.JPEG",
    "wnid": "n02058221",
    "true_label": "albatross",
    "predicted_index": 146,
    "predicted_label": "albatross",
    "correct": true
  },
  {
    "image": "ILSVRC2012_val_00034223.JPEG",
    "wnid": "n02058221",
    "true_label": "albatross",
    "predicted_index": 146,
    "predicted_label": "albatross",
    "correct": true
  },
  {
    "image": "ILSVRC2012_val_00035517.JPEG",
    "wnid": "n02058221",
    "true_label": "albatross",
    "predicted_index": 146,
    "predicted_label": "albatross",
    "correct": true
  },
  {
    "image": "ILSVRC2012_val_00035766.JPEG",
    "wnid": "n02058221",
    "true_label": "albatross",
    "predicted_index": 146,
    "predicted_label": "albatross",
    "correct": true
  },
  {
    "image": "ILSVRC2012_val_00036511.JPEG",
    "wnid": "n02058221",
    "true_label": "albatross",
    "predicted_index": 146,
    "predicted_label": "albatross",
    "correct": true
  },
  {
    "image": "ILSVRC2012_val_00037746.JPEG",
    "wnid": "n02058221",
    "true_label": "albatross",
    "predicted_index": 146,
    "predicted_label": "albatross",
    "correct": true
  },
  {
    "image": "ILSVRC2012_val_00038241.JPEG",
    "wnid": "n02058221",
    "true_label": "albatross",
    "predicted_index": 146,
    "predicted_label": "albatross",
    "correct": true
  },
  {
    "image": "ILSVRC2012_val_00038725.JPEG",
    "wnid": "n02058221",
    "true_label": "albatross",
    "predicted_index": 89,
    "predicted_label": "sulphur-crested cockatoo",
    "correct": false
  },
  {
    "image": "ILSVRC2012_val_00038864.JPEG",
    "wnid": "n02058221",
    "true_label": "albatross",
    "predicted_index": 146,
    "predicted_label": "albatross",
    "correct": true
  },
  {
    "image": "ILSVRC2012_val_00039539.JPEG",
    "wnid": "n02058221",
    "true_label": "albatross",
    "predicted_index": 146,
    "predicted_label": "albatross",
    "correct": true
  },
  {
    "image": "ILSVRC2012_val_00040987.JPEG",
    "wnid": "n02058221",
    "true_label": "albatross",
    "predicted_index": 146,
    "predicted_label": "albatross",
    "correct": true
  },
  {
    "image": "ILSVRC2012_val_00043108.JPEG",
    "wnid": "n02058221",
    "true_label": "albatross",
    "predicted_index": 146,
    "predicted_label": "albatross",
    "correct": true
  },
  {
    "image": "ILSVRC2012_val_00044749.JPEG",
    "wnid": "n02058221",
    "true_label": "albatross",
    "predicted_index": 146,
    "predicted_label": "albatross",
    "correct": true
  },
  {
    "image": "ILSVRC2012_val_00046647.JPEG",
    "wnid": "n02058221",
    "true_label": "albatross",
    "predicted_index": 146,
    "predicted_label": "albatross",
    "correct": true
  },
  {
    "image": "ILSVRC2012_val_00048172.JPEG",
    "wnid": "n02058221",
    "true_label": "albatross",
    "predicted_index": 146,
    "predicted_label": "albatross",
    "correct": true
  },
  {
    "image": "ILSVRC2012_val_00048348.JPEG",
    "wnid": "n02058221",
    "true_label": "albatross",
    "predicted_index": 146,
    "predicted_label": "albatross",
    "correct": true
  },
  {
    "image": "ILSVRC2012_val_00048468.JPEG",
    "wnid": "n02058221",
    "true_label": "albatross",
    "predicted_index": 146,
    "predicted_label": "albatross",
    "correct": true
  },
  {
    "image": "ILSVRC2012_val_00049170.JPEG",
    "wnid": "n02058221",
    "true_label": "albatross",
    "predicted_index": 144,
    "predicted_label": "pelican",
    "correct": false
  },
  {
    "image": "ILSVRC2012_val_00000236.JPEG",
    "wnid": "n01443537",
    "true_label": "goldfish",
    "predicted_index": 115,
    "predicted_label": "sea slug",
    "correct": false
  },
  {
    "image": "ILSVRC2012_val_00000262.JPEG",
    "wnid": "n01443537",
    "true_label": "goldfish",
    "predicted_index": 1,
    "predicted_label": "goldfish",
    "correct": true
  },
  {
    "image": "ILSVRC2012_val_00000307.JPEG",
    "wnid": "n01443537",
    "true_label": "goldfish",
    "predicted_index": 1,
    "predicted_label": "goldfish",
    "correct": true
  },
  {
    "image": "ILSVRC2012_val_00000994.JPEG",
    "wnid": "n01443537",
    "true_label": "goldfish",
    "predicted_index": 1,
    "predicted_label": "goldfish",
    "correct": true
  },
  {
    "image": "ILSVRC2012_val_00002241.JPEG",
    "wnid": "n01443537",
    "true_label": "goldfish",
    "predicted_index": 467,
    "predicted_label": "butcher shop",
    "correct": false
  },
  {
    "image": "ILSVRC2012_val_00002848.JPEG",
    "wnid": "n01443537",
    "true_label": "goldfish",
    "predicted_index": 1,
    "predicted_label": "goldfish",
    "correct": true
  },
  {
    "image": "ILSVRC2012_val_00003150.JPEG",
    "wnid": "n01443537",
    "true_label": "goldfish",
    "predicted_index": 1,
    "predicted_label": "goldfish",
    "correct": true
  },
  {
    "image": "ILSVRC2012_val_00003735.JPEG",
    "wnid": "n01443537",
    "true_label": "goldfish",
    "predicted_index": 1,
    "predicted_label": "goldfish",
    "correct": true
  },
  {
    "image": "ILSVRC2012_val_00004655.JPEG",
    "wnid": "n01443537",
    "true_label": "goldfish",
    "predicted_index": 1,
    "predicted_label": "goldfish",
    "correct": true
  },
  {
    "image": "ILSVRC2012_val_00004677.JPEG",
    "wnid": "n01443537",
    "true_label": "goldfish",
    "predicted_index": 1,
    "predicted_label": "goldfish",
    "correct": true
  },
  {
    "image": "ILSVRC2012_val_00005870.JPEG",
    "wnid": "n01443537",
    "true_label": "goldfish",
    "predicted_index": 1,
    "predicted_label": "goldfish",
    "correct": true
  },
  {
    "image": "ILSVRC2012_val_00006007.JPEG",
    "wnid": "n01443537",
    "true_label": "goldfish",
    "predicted_index": 111,
    "predicted_label": "nematode",
    "correct": false
  },
  {
    "image": "ILSVRC2012_val_00006216.JPEG",
    "wnid": "n01443537",
    "true_label": "goldfish",
    "predicted_index": 1,
    "predicted_label": "goldfish",
    "correct": true
  },
  {
    "image": "ILSVRC2012_val_00009034.JPEG",
    "wnid": "n01443537",
    "true_label": "goldfish",
    "predicted_index": 1,
    "predicted_label": "goldfish",
    "correct": true
  },
  {
    "image": "ILSVRC2012_val_00010363.JPEG",
    "wnid": "n01443537",
    "true_label": "goldfish",
    "predicted_index": 883,
    "predicted_label": "vase",
    "correct": false
  },
  {
    "image": "ILSVRC2012_val_00010509.JPEG",
    "wnid": "n01443537",
    "true_label": "goldfish",
    "predicted_index": 1,
    "predicted_label": "goldfish",
    "correct": true
  },
  {
    "image": "ILSVRC2012_val_00011914.JPEG",
    "wnid": "n01443537",
    "true_label": "goldfish",
    "predicted_index": 1,
    "predicted_label": "goldfish",
    "correct": true
  },
  {
    "image": "ILSVRC2012_val_00012880.JPEG",
    "wnid": "n01443537",
    "true_label": "goldfish",
    "predicted_index": 36,
    "predicted_label": "terrapin",
    "correct": false
  },
  {
    "image": "ILSVRC2012_val_00013513.JPEG",
    "wnid": "n01443537",
    "true_label": "goldfish",
    "predicted_index": 1,
    "predicted_label": "goldfish",
    "correct": true
  },
  {
    "image": "ILSVRC2012_val_00013623.JPEG",
    "wnid": "n01443537",
    "true_label": "goldfish",
    "predicted_index": 1,
    "predicted_label": "goldfish",
    "correct": true
  },
  {
    "image": "ILSVRC2012_val_00016962.JPEG",
    "wnid": "n01443537",
    "true_label": "goldfish",
    "predicted_index": 1,
    "predicted_label": "goldfish",
    "correct": true
  },
  {
    "image": "ILSVRC2012_val_00018075.JPEG",
    "wnid": "n01443537",
    "true_label": "goldfish",
    "predicted_index": 1,
    "predicted_label": "goldfish",
    "correct": true
  },
  {
    "image": "ILSVRC2012_val_00019459.JPEG",
    "wnid": "n01443537",
    "true_label": "goldfish",
    "predicted_index": 1,
    "predicted_label": "goldfish",
    "correct": true
  },
  {
    "image": "ILSVRC2012_val_00020436.JPEG",
    "wnid": "n01443537",
    "true_label": "goldfish",
    "predicted_index": 6,
    "predicted_label": "stingray",
    "correct": false
  },
  {
    "image": "ILSVRC2012_val_00020785.JPEG",
    "wnid": "n01443537",
    "true_label": "goldfish",
    "predicted_index": 1,
    "predicted_label": "goldfish",
    "correct": true
  },
  {
    "image": "ILSVRC2012_val_00020822.JPEG",
    "wnid": "n01443537",
    "true_label": "goldfish",
    "predicted_index": 1,
    "predicted_label": "goldfish",
    "correct": true
  },
  {
    "image": "ILSVRC2012_val_00021905.JPEG",
    "wnid": "n01443537",
    "true_label": "goldfish",
    "predicted_index": 1,
    "predicted_label": "goldfish",
    "correct": true
  },
  {
    "image": "ILSVRC2012_val_00022138.JPEG",
    "wnid": "n01443537",
    "true_label": "goldfish",
    "predicted_index": 1,
    "predicted_label": "goldfish",
    "correct": true
  },
  {
    "image": "ILSVRC2012_val_00023869.JPEG",
    "wnid": "n01443537",
    "true_label": "goldfish",
    "predicted_index": 1,
    "predicted_label": "goldfish",
    "correct": true
  },
  {
    "image": "ILSVRC2012_val_00028713.JPEG",
    "wnid": "n01443537",
    "true_label": "goldfish",
    "predicted_index": 1,
    "predicted_label": "goldfish",
    "correct": true
  },
  {
    "image": "ILSVRC2012_val_00030060.JPEG",
    "wnid": "n01443537",
    "true_label": "goldfish",
    "predicted_index": 1,
    "predicted_label": "goldfish",
    "correct": true
  },
  {
    "image": "ILSVRC2012_val_00030217.JPEG",
    "wnid": "n01443537",
    "true_label": "goldfish",
    "predicted_index": 1,
    "predicted_label": "goldfish",
    "correct": true
  },
  {
    "image": "ILSVRC2012_val_00031138.JPEG",
    "wnid": "n01443537",
    "true_label": "goldfish",
    "predicted_index": 1,
    "predicted_label": "goldfish",
    "correct": true
  },
  {
    "image": "ILSVRC2012_val_00032235.JPEG",
    "wnid": "n01443537",
    "true_label": "goldfish",
    "predicted_index": 1,
    "predicted_label": "goldfish",
    "correct": true
  },
  {
    "image": "ILSVRC2012_val_00032258.JPEG",
    "wnid": "n01443537",
    "true_label": "goldfish",
    "predicted_index": 1,
    "predicted_label": "goldfish",
    "correct": true
  },
  {
    "image": "ILSVRC2012_val_00032675.JPEG",
    "wnid": "n01443537",
    "true_label": "goldfish",
    "predicted_index": 1,
    "predicted_label": "goldfish",
    "correct": true
  },
  {
    "image": "ILSVRC2012_val_00034386.JPEG",
    "wnid": "n01443537",
    "true_label": "goldfish",
    "predicted_index": 1,
    "predicted_label": "goldfish",
    "correct": true
  },
  {
    "image": "ILSVRC2012_val_00037846.JPEG",
    "wnid": "n01443537",
    "true_label": "goldfish",
    "predicted_index": 1,
    "predicted_label": "goldfish",
    "correct": true
  },
  {
    "image": "ILSVRC2012_val_00038057.JPEG",
    "wnid": "n01443537",
    "true_label": "goldfish",
    "predicted_index": 301,
    "predicted_label": "ladybug",
    "correct": false
  },
  {
    "image": "ILSVRC2012_val_00044095.JPEG",
    "wnid": "n01443537",
    "true_label": "goldfish",
    "predicted_index": 1,
    "predicted_label": "goldfish",
    "correct": true
  },
  {
    "image": "ILSVRC2012_val_00045761.JPEG",
    "wnid": "n01443537",
    "true_label": "goldfish",
    "predicted_index": 1,
    "predicted_label": "goldfish",
    "correct": true
  },
  {
    "image": "ILSVRC2012_val_00046915.JPEG",
    "wnid": "n01443537",
    "true_label": "goldfish",
    "predicted_index": 1,
    "predicted_label": "goldfish",
    "correct": true
  },
  {
    "image": "ILSVRC2012_val_00046969.JPEG",
    "wnid": "n01443537",
    "true_label": "goldfish",
    "predicted_index": 1,
    "predicted_label": "goldfish",
    "correct": true
  },
  {
    "image": "ILSVRC2012_val_00047396.JPEG",
    "wnid": "n01443537",
    "true_label": "goldfish",
    "predicted_index": 1,
    "predicted_label": "goldfish",
    "correct": true
  },
  {
    "image": "ILSVRC2012_val_00047561.JPEG",
    "wnid": "n01443537",
    "true_label": "goldfish",
    "predicted_index": 1,
    "predicted_label": "goldfish",
    "correct": true
  },
  {
    "image": "ILSVRC2012_val_00048840.JPEG",
    "wnid": "n01443537",
    "true_label": "goldfish",
    "predicted_index": 1,
    "predicted_label": "goldfish",
    "correct": true
  },
  {
    "image": "ILSVRC2012_val_00048864.JPEG",
    "wnid": "n01443537",
    "true_label": "goldfish",
    "predicted_index": 1,
    "predicted_label": "goldfish",
    "correct": true
  },
  {
    "image": "ILSVRC2012_val_00049585.JPEG",
    "wnid": "n01443537",
    "true_label": "goldfish",
    "predicted_index": 1,
    "predicted_label": "goldfish",
    "correct": true
  },
  {
    "image": "ILSVRC2012_val_00049617.JPEG",
    "wnid": "n01443537",
    "true_label": "goldfish",
    "predicted_index": 1,
    "predicted_label": "goldfish",
    "correct": true
  },
  {
    "image": "ILSVRC2012_val_00049712.JPEG",
    "wnid": "n01443537",
    "true_label": "goldfish",
    "predicted_index": 394,
    "predicted_label": "sturgeon",
    "correct": false
  },
  {
    "image": "ILSVRC2012_val_00000679.JPEG",
    "wnid": "n01776313",
    "true_label": "tick",
    "predicted_index": 78,
    "predicted_label": "tick",
    "correct": true
  },
  {
    "image": "ILSVRC2012_val_00000943.JPEG",
    "wnid": "n01776313",
    "true_label": "tick",
    "predicted_index": 78,
    "predicted_label": "tick",
    "correct": true
  },
  {
    "image": "ILSVRC2012_val_00001283.JPEG",
    "wnid": "n01776313",
    "true_label": "tick",
    "predicted_index": 78,
    "predicted_label": "tick",
    "correct": true
  },
  {
    "image": "ILSVRC2012_val_00001760.JPEG",
    "wnid": "n01776313",
    "true_label": "tick",
    "predicted_index": 78,
    "predicted_label": "tick",
    "correct": true
  },
  {
    "image": "ILSVRC2012_val_00001766.JPEG",
    "wnid": "n01776313",
    "true_label": "tick",
    "predicted_index": 304,
    "predicted_label": "leaf beetle",
    "correct": false
  },
  {
    "image": "ILSVRC2012_val_00002957.JPEG",
    "wnid": "n01776313",
    "true_label": "tick",
    "predicted_index": 78,
    "predicted_label": "tick",
    "correct": true
  },
  {
    "image": "ILSVRC2012_val_00003577.JPEG",
    "wnid": "n01776313",
    "true_label": "tick",
    "predicted_index": 78,
    "predicted_label": "tick",
    "correct": true
  },
  {
    "image": "ILSVRC2012_val_00004095.JPEG",
    "wnid": "n01776313",
    "true_label": "tick",
    "predicted_index": 72,
    "predicted_label": "black and gold garden spider",
    "correct": false
  },
  {
    "image": "ILSVRC2012_val_00004722.JPEG",
    "wnid": "n01776313",
    "true_label": "tick",
    "predicted_index": 78,
    "predicted_label": "tick",
    "correct": true
  },
  {
    "image": "ILSVRC2012_val_00005788.JPEG",
    "wnid": "n01776313",
    "true_label": "tick",
    "predicted_index": 78,
    "predicted_label": "tick",
    "correct": true
  },
  {
    "image": "ILSVRC2012_val_00005932.JPEG",
    "wnid": "n01776313",
    "true_label": "tick",
    "predicted_index": 320,
    "predicted_label": "damselfly",
    "correct": false
  },
  {
    "image": "ILSVRC2012_val_00007065.JPEG",
    "wnid": "n01776313",
    "true_label": "tick",
    "predicted_index": 78,
    "predicted_label": "tick",
    "correct": true
  },
  {
    "image": "ILSVRC2012_val_00008054.JPEG",
    "wnid": "n01776313",
    "true_label": "tick",
    "predicted_index": 78,
    "predicted_label": "tick",
    "correct": true
  },
  {
    "image": "ILSVRC2012_val_00009192.JPEG",
    "wnid": "n01776313",
    "true_label": "tick",
    "predicted_index": 78,
    "predicted_label": "tick",
    "correct": true
  },
  {
    "image": "ILSVRC2012_val_00013330.JPEG",
    "wnid": "n01776313",
    "true_label": "tick",
    "predicted_index": 73,
    "predicted_label": "barn spider",
    "correct": false
  },
  {
    "image": "ILSVRC2012_val_00013600.JPEG",
    "wnid": "n01776313",
    "true_label": "tick",
    "predicted_index": 78,
    "predicted_label": "tick",
    "correct": true
  },
  {
    "image": "ILSVRC2012_val_00013917.JPEG",
    "wnid": "n01776313",
    "true_label": "tick",
    "predicted_index": 78,
    "predicted_label": "tick",
    "correct": true
  },
  {
    "image": "ILSVRC2012_val_00014587.JPEG",
    "wnid": "n01776313",
    "true_label": "tick",
    "predicted_index": 78,
    "predicted_label": "tick",
    "correct": true
  },
  {
    "image": "ILSVRC2012_val_00015127.JPEG",
    "wnid": "n01776313",
    "true_label": "tick",
    "predicted_index": 78,
    "predicted_label": "tick",
    "correct": true
  },
  {
    "image": "ILSVRC2012_val_00015564.JPEG",
    "wnid": "n01776313",
    "true_label": "tick",
    "predicted_index": 78,
    "predicted_label": "tick",
    "correct": true
  },
  {
    "image": "ILSVRC2012_val_00016227.JPEG",
    "wnid": "n01776313",
    "true_label": "tick",
    "predicted_index": 70,
    "predicted_label": "harvestman",
    "correct": false
  },
  {
    "image": "ILSVRC2012_val_00018137.JPEG",
    "wnid": "n01776313",
    "true_label": "tick",
    "predicted_index": 78,
    "predicted_label": "tick",
    "correct": true
  },
  {
    "image": "ILSVRC2012_val_00018963.JPEG",
    "wnid": "n01776313",
    "true_label": "tick",
    "predicted_index": 78,
    "predicted_label": "tick",
    "correct": true
  },
  {
    "image": "ILSVRC2012_val_00020115.JPEG",
    "wnid": "n01776313",
    "true_label": "tick",
    "predicted_index": 78,
    "predicted_label": "tick",
    "correct": true
  },
  {
    "image": "ILSVRC2012_val_00020692.JPEG",
    "wnid": "n01776313",
    "true_label": "tick",
    "predicted_index": 77,
    "predicted_label": "wolf spider",
    "correct": false
  },
  {
    "image": "ILSVRC2012_val_00021337.JPEG",
    "wnid": "n01776313",
    "true_label": "tick",
    "predicted_index": 78,
    "predicted_label": "tick",
    "correct": true
  },
  {
    "image": "ILSVRC2012_val_00021525.JPEG",
    "wnid": "n01776313",
    "true_label": "tick",
    "predicted_index": 78,
    "predicted_label": "tick",
    "correct": true
  },
  {
    "image": "ILSVRC2012_val_00023434.JPEG",
    "wnid": "n01776313",
    "true_label": "tick",
    "predicted_index": 78,
    "predicted_label": "tick",
    "correct": true
  },
  {
    "image": "ILSVRC2012_val_00023564.JPEG",
    "wnid": "n01776313",
    "true_label": "tick",
    "predicted_index": 78,
    "predicted_label": "tick",
    "correct": true
  },
  {
    "image": "ILSVRC2012_val_00027940.JPEG",
    "wnid": "n01776313",
    "true_label": "tick",
    "predicted_index": 78,
    "predicted_label": "tick",
    "correct": true
  },
  {
    "image": "ILSVRC2012_val_00029069.JPEG",
    "wnid": "n01776313",
    "true_label": "tick",
    "predicted_index": 363,
    "predicted_label": "armadillo",
    "correct": false
  },
  {
    "image": "ILSVRC2012_val_00030444.JPEG",
    "wnid": "n01776313",
    "true_label": "tick",
    "predicted_index": 78,
    "predicted_label": "tick",
    "correct": true
  },
  {
    "image": "ILSVRC2012_val_00030916.JPEG",
    "wnid": "n01776313",
    "true_label": "tick",
    "predicted_index": 314,
    "predicted_label": "cockroach",
    "correct": false
  },
  {
    "image": "ILSVRC2012_val_00031374.JPEG",
    "wnid": "n01776313",
    "true_label": "tick",
    "predicted_index": 78,
    "predicted_label": "tick",
    "correct": true
  },
  {
    "image": "ILSVRC2012_val_00032343.JPEG",
    "wnid": "n01776313",
    "true_label": "tick",
    "predicted_index": 70,
    "predicted_label": "harvestman",
    "correct": false
  },
  {
    "image": "ILSVRC2012_val_00032783.JPEG",
    "wnid": "n01776313",
    "true_label": "tick",
    "predicted_index": 78,
    "predicted_label": "tick",
    "correct": true
  },
  {
    "image": "ILSVRC2012_val_00032902.JPEG",
    "wnid": "n01776313",
    "true_label": "tick",
    "predicted_index": 78,
    "predicted_label": "tick",
    "correct": true
  },
  {
    "image": "ILSVRC2012_val_00034020.JPEG",
    "wnid": "n01776313",
    "true_label": "tick",
    "predicted_index": 70,
    "predicted_label": "harvestman",
    "correct": false
  },
  {
    "image": "ILSVRC2012_val_00035573.JPEG",
    "wnid": "n01776313",
    "true_label": "tick",
    "predicted_index": 892,
    "predicted_label": "wall clock",
    "correct": false
  },
  {
    "image": "ILSVRC2012_val_00037297.JPEG",
    "wnid": "n01776313",
    "true_label": "tick",
    "predicted_index": 78,
    "predicted_label": "tick",
    "correct": true
  },
  {
    "image": "ILSVRC2012_val_00037933.JPEG",
    "wnid": "n01776313",
    "true_label": "tick",
    "predicted_index": 78,
    "predicted_label": "tick",
    "correct": true
  },
  {
    "image": "ILSVRC2012_val_00040519.JPEG",
    "wnid": "n01776313",
    "true_label": "tick",
    "predicted_index": 301,
    "predicted_label": "ladybug",
    "correct": false
  },
  {
    "image": "ILSVRC2012_val_00040584.JPEG",
    "wnid": "n01776313",
    "true_label": "tick",
    "predicted_index": 77,
    "predicted_label": "wolf spider",
    "correct": false
  },
  {
    "image": "ILSVRC2012_val_00041549.JPEG",
    "wnid": "n01776313",
    "true_label": "tick",
    "predicted_index": 78,
    "predicted_label": "tick",
    "correct": true
  },
  {
    "image": "ILSVRC2012_val_00042899.JPEG",
    "wnid": "n01776313",
    "true_label": "tick",
    "predicted_index": 78,
    "predicted_label": "tick",
    "correct": true
  },
  {
    "image": "ILSVRC2012_val_00043155.JPEG",
    "wnid": "n01776313",
    "true_label": "tick",
    "predicted_index": 72,
    "predicted_label": "black and gold garden spider",
    "correct": false
  },
  {
    "image": "ILSVRC2012_val_00046529.JPEG",
    "wnid": "n01776313",
    "true_label": "tick",
    "predicted_index": 818,
    "predicted_label": "spotlight",
    "correct": false
  },
  {
    "image": "ILSVRC2012_val_00046868.JPEG",
    "wnid": "n01776313",
    "true_label": "tick",
    "predicted_index": 78,
    "predicted_label": "tick",
    "correct": true
  },
  {
    "image": "ILSVRC2012_val_00048593.JPEG",
    "wnid": "n01776313",
    "true_label": "tick",
    "predicted_index": 78,
    "predicted_label": "tick",
    "correct": true
  },
  {
    "image": "ILSVRC2012_val_00049535.JPEG",
    "wnid": "n01776313",
    "true_label": "tick",
    "predicted_index": 71,
    "predicted_label": "scorpion",
    "correct": false
  },
  {
    "image": "ILSVRC2012_val_00000033.JPEG",
    "wnid": "n02077923",
    "true_label": "sea lion",
    "predicted_index": 360,
    "predicted_label": "otter",
    "correct": false
  },
  {
    "image": "ILSVRC2012_val_00001472.JPEG",
    "wnid": "n02077923",
    "true_label": "sea lion",
    "predicted_index": 150,
    "predicted_label": "sea lion",
    "correct": true
  },
  {
    "image": "ILSVRC2012_val_00002504.JPEG",
    "wnid": "n02077923",
    "true_label": "sea lion",
    "predicted_index": 150,
    "predicted_label": "sea lion",
    "correct": true
  },
  {
    "image": "ILSVRC2012_val_00003149.JPEG",
    "wnid": "n02077923",
    "true_label": "sea lion",
    "predicted_index": 150,
    "predicted_label": "sea lion",
    "correct": true
  },
  {
    "image": "ILSVRC2012_val_00003335.JPEG",
    "wnid": "n02077923",
    "true_label": "sea lion",
    "predicted_index": 150,
    "predicted_label": "sea lion",
    "correct": true
  },
  {
    "image": "ILSVRC2012_val_00003574.JPEG",
    "wnid": "n02077923",
    "true_label": "sea lion",
    "predicted_index": 150,
    "predicted_label": "sea lion",
    "correct": true
  },
  {
    "image": "ILSVRC2012_val_00004302.JPEG",
    "wnid": "n02077923",
    "true_label": "sea lion",
    "predicted_index": 150,
    "predicted_label": "sea lion",
    "correct": true
  },
  {
    "image": "ILSVRC2012_val_00005360.JPEG",
    "wnid": "n02077923",
    "true_label": "sea lion",
    "predicted_index": 150,
    "predicted_label": "sea lion",
    "correct": true
  },
  {
    "image": "ILSVRC2012_val_00007193.JPEG",
    "wnid": "n02077923",
    "true_label": "sea lion",
    "predicted_index": 2,
    "predicted_label": "great white shark",
    "correct": false
  },
  {
    "image": "ILSVRC2012_val_00011255.JPEG",
    "wnid": "n02077923",
    "true_label": "sea lion",
    "predicted_index": 150,
    "predicted_label": "sea lion",
    "correct": true
  },
  {
    "image": "ILSVRC2012_val_00012176.JPEG",
    "wnid": "n02077923",
    "true_label": "sea lion",
    "predicted_index": 394,
    "predicted_label": "sturgeon",
    "correct": false
  },
  {
    "image": "ILSVRC2012_val_00012330.JPEG",
    "wnid": "n02077923",
    "true_label": "sea lion",
    "predicted_index": 150,
    "predicted_label": "sea lion",
    "correct": true
  },
  {
    "image": "ILSVRC2012_val_00013004.JPEG",
    "wnid": "n02077923",
    "true_label": "sea lion",
    "predicted_index": 150,
    "predicted_label": "sea lion",
    "correct": true
  },
  {
    "image": "ILSVRC2012_val_00013809.JPEG",
    "wnid": "n02077923",
    "true_label": "sea lion",
    "predicted_index": 150,
    "predicted_label": "sea lion",
    "correct": true
  },
  {
    "image": "ILSVRC2012_val_00015925.JPEG",
    "wnid": "n02077923",
    "true_label": "sea lion",
    "predicted_index": 150,
    "predicted_label": "sea lion",
    "correct": true
  },
  {
    "image": "ILSVRC2012_val_00017786.JPEG",
    "wnid": "n02077923",
    "true_label": "sea lion",
    "predicted_index": 34,
    "predicted_label": "leatherback turtle",
    "correct": false
  },
  {
    "image": "ILSVRC2012_val_00020975.JPEG",
    "wnid": "n02077923",
    "true_label": "sea lion",
    "predicted_index": 150,
    "predicted_label": "sea lion",
    "correct": true
  },
  {
    "image": "ILSVRC2012_val_00021764.JPEG",
    "wnid": "n02077923",
    "true_label": "sea lion",
    "predicted_index": 976,
    "predicted_label": "promontory",
    "correct": false
  },
  {
    "image": "ILSVRC2012_val_00022358.JPEG",
    "wnid": "n02077923",
    "true_label": "sea lion",
    "predicted_index": 150,
    "predicted_label": "sea lion",
    "correct": true
  },
  {
    "image": "ILSVRC2012_val_00022732.JPEG",
    "wnid": "n02077923",
    "true_label": "sea lion",
    "predicted_index": 150,
    "predicted_label": "sea lion",
    "correct": true
  },
  {
    "image": "ILSVRC2012_val_00023070.JPEG",
    "wnid": "n02077923",
    "true_label": "sea lion",
    "predicted_index": 150,
    "predicted_label": "sea lion",
    "correct": true
  },
  {
    "image": "ILSVRC2012_val_00023081.JPEG",
    "wnid": "n02077923",
    "true_label": "sea lion",
    "predicted_index": 150,
    "predicted_label": "sea lion",
    "correct": true
  },
  {
    "image": "ILSVRC2012_val_00025926.JPEG",
    "wnid": "n02077923",
    "true_label": "sea lion",
    "predicted_index": 150,
    "predicted_label": "sea lion",
    "correct": true
  },
  {
    "image": "ILSVRC2012_val_00026125.JPEG",
    "wnid": "n02077923",
    "true_label": "sea lion",
    "predicted_index": 801,
    "predicted_label": "snorkel",
    "correct": false
  },
  {
    "image": "ILSVRC2012_val_00026339.JPEG",
    "wnid": "n02077923",
    "true_label": "sea lion",
    "predicted_index": 150,
    "predicted_label": "sea lion",
    "correct": true
  },
  {
    "image": "ILSVRC2012_val_00026593.JPEG",
    "wnid": "n02077923",
    "true_label": "sea lion",
    "predicted_index": 150,
    "predicted_label": "sea lion",
    "correct": true
  },
  {
    "image": "ILSVRC2012_val_00027024.JPEG",
    "wnid": "n02077923",
    "true_label": "sea lion",
    "predicted_index": 150,
    "predicted_label": "sea lion",
    "correct": true
  },
  {
    "image": "ILSVRC2012_val_00027457.JPEG",
    "wnid": "n02077923",
    "true_label": "sea lion",
    "predicted_index": 150,
    "predicted_label": "sea lion",
    "correct": true
  },
  {
    "image": "ILSVRC2012_val_00027866.JPEG",
    "wnid": "n02077923",
    "true_label": "sea lion",
    "predicted_index": 150,
    "predicted_label": "sea lion",
    "correct": true
  },
  {
    "image": "ILSVRC2012_val_00029409.JPEG",
    "wnid": "n02077923",
    "true_label": "sea lion",
    "predicted_index": 150,
    "predicted_label": "sea lion",
    "correct": true
  },
  {
    "image": "ILSVRC2012_val_00029634.JPEG",
    "wnid": "n02077923",
    "true_label": "sea lion",
    "predicted_index": 150,
    "predicted_label": "sea lion",
    "correct": true
  },
  {
    "image": "ILSVRC2012_val_00030365.JPEG",
    "wnid": "n02077923",
    "true_label": "sea lion",
    "predicted_index": 150,
    "predicted_label": "sea lion",
    "correct": true
  },
  {
    "image": "ILSVRC2012_val_00030675.JPEG",
    "wnid": "n02077923",
    "true_label": "sea lion",
    "predicted_index": 150,
    "predicted_label": "sea lion",
    "correct": true
  },
  {
    "image": "ILSVRC2012_val_00032166.JPEG",
    "wnid": "n02077923",
    "true_label": "sea lion",
    "predicted_index": 150,
    "predicted_label": "sea lion",
    "correct": true
  },
  {
    "image": "ILSVRC2012_val_00032540.JPEG",
    "wnid": "n02077923",
    "true_label": "sea lion",
    "predicted_index": 150,
    "predicted_label": "sea lion",
    "correct": true
  },
  {
    "image": "ILSVRC2012_val_00032816.JPEG",
    "wnid": "n02077923",
    "true_label": "sea lion",
    "predicted_index": 562,
    "predicted_label": "fountain",
    "correct": false
  },
  {
    "image": "ILSVRC2012_val_00033000.JPEG",
    "wnid": "n02077923",
    "true_label": "sea lion",
    "predicted_index": 150,
    "predicted_label": "sea lion",
    "correct": true
  },
  {
    "image": "ILSVRC2012_val_00038217.JPEG",
    "wnid": "n02077923",
    "true_label": "sea lion",
    "predicted_index": 150,
    "predicted_label": "sea lion",
    "correct": true
  },
  {
    "image": "ILSVRC2012_val_00038371.JPEG",
    "wnid": "n02077923",
    "true_label": "sea lion",
    "predicted_index": 51,
    "predicted_label": "triceratops",
    "correct": false
  },
  {
    "image": "ILSVRC2012_val_00038726.JPEG",
    "wnid": "n02077923",
    "true_label": "sea lion",
    "predicted_index": 150,
    "predicted_label": "sea lion",
    "correct": true
  },
  {
    "image": "ILSVRC2012_val_00039641.JPEG",
    "wnid": "n02077923",
    "true_label": "sea lion",
    "predicted_index": 150,
    "predicted_label": "sea lion",
    "correct": true
  },
  {
    "image": "ILSVRC2012_val_00041773.JPEG",
    "wnid": "n02077923",
    "true_label": "sea lion",
    "predicted_index": 976,
    "predicted_label": "promontory",
    "correct": false
  },
  {
    "image": "ILSVRC2012_val_00043231.JPEG",
    "wnid": "n02077923",
    "true_label": "sea lion",
    "predicted_index": 150,
    "predicted_label": "sea lion",
    "correct": true
  },
  {
    "image": "ILSVRC2012_val_00043549.JPEG",
    "wnid": "n02077923",
    "true_label": "sea lion",
    "predicted_index": 150,
    "predicted_label": "sea lion",
    "correct": true
  },
  {
    "image": "ILSVRC2012_val_00044328.JPEG",
    "wnid": "n02077923",
    "true_label": "sea lion",
    "predicted_index": 360,
    "predicted_label": "otter",
    "correct": false
  },
  {
    "image": "ILSVRC2012_val_00045435.JPEG",
    "wnid": "n02077923",
    "true_label": "sea lion",
    "predicted_index": 150,
    "predicted_label": "sea lion",
    "correct": true
  },
  {
    "image": "ILSVRC2012_val_00046758.JPEG",
    "wnid": "n02077923",
    "true_label": "sea lion",
    "predicted_index": 150,
    "predicted_label": "sea lion",
    "correct": true
  },
  {
    "image": "ILSVRC2012_val_00046767.JPEG",
    "wnid": "n02077923",
    "true_label": "sea lion",
    "predicted_index": 344,
    "predicted_label": "hippopotamus",
    "correct": false
  },
  {
    "image": "ILSVRC2012_val_00047983.JPEG",
    "wnid": "n02077923",
    "true_label": "sea lion",
    "predicted_index": 150,
    "predicted_label": "sea lion",
    "correct": true
  },
  {
    "image": "ILSVRC2012_val_00048240.JPEG",
    "wnid": "n02077923",
    "true_label": "sea lion",
    "predicted_index": 344,
    "predicted_label": "hippopotamus",
    "correct": false
  },
  {
    "image": "ILSVRC2012_val_00000043.JPEG",
    "wnid": "n02006656",
    "true_label": "spoonbill",
    "predicted_index": 129,
    "predicted_label": "spoonbill",
    "correct": true
  },
  {
    "image": "ILSVRC2012_val_00000593.JPEG",
    "wnid": "n02006656",
    "true_label": "spoonbill",
    "predicted_index": 132,
    "predicted_label": "American egret",
    "correct": false
  },
  {
    "image": "ILSVRC2012_val_00000735.JPEG",
    "wnid": "n02006656",
    "true_label": "spoonbill",
    "predicted_index": 129,
    "predicted_label": "spoonbill",
    "correct": true
  },
  {
    "image": "ILSVRC2012_val_00000774.JPEG",
    "wnid": "n02006656",
    "true_label": "spoonbill",
    "predicted_index": 99,
    "predicted_label": "goose",
    "correct": false
  },
  {
    "image": "ILSVRC2012_val_00000878.JPEG",
    "wnid": "n02006656",
    "true_label": "spoonbill",
    "predicted_index": 129,
    "predicted_label": "spoonbill",
    "correct": true
  },
  {
    "image": "ILSVRC2012_val_00002192.JPEG",
    "wnid": "n02006656",
    "true_label": "spoonbill",
    "predicted_index": 129,
    "predicted_label": "spoonbill",
    "correct": true
  },
  {
    "image": "ILSVRC2012_val_00002953.JPEG",
    "wnid": "n02006656",
    "true_label": "spoonbill",
    "predicted_index": 129,
    "predicted_label": "spoonbill",
    "correct": true
  },
  {
    "image": "ILSVRC2012_val_00005107.JPEG",
    "wnid": "n02006656",
    "true_label": "spoonbill",
    "predicted_index": 129,
    "predicted_label": "spoonbill",
    "correct": true
  },
  {
    "image": "ILSVRC2012_val_00005186.JPEG",
    "wnid": "n02006656",
    "true_label": "spoonbill",
    "predicted_index": 129,
    "predicted_label": "spoonbill",
    "correct": true
  },
  {
    "image": "ILSVRC2012_val_00005379.JPEG",
    "wnid": "n02006656",
    "true_label": "spoonbill",
    "predicted_index": 129,
    "predicted_label": "spoonbill",
    "correct": true
  },
  {
    "image": "ILSVRC2012_val_00005830.JPEG",
    "wnid": "n02006656",
    "true_label": "spoonbill",
    "predicted_index": 129,
    "predicted_label": "spoonbill",
    "correct": true
  },
  {
    "image": "ILSVRC2012_val_00007697.JPEG",
    "wnid": "n02006656",
    "true_label": "spoonbill",
    "predicted_index": 129,
    "predicted_label": "spoonbill",
    "correct": true
  },
  {
    "image": "ILSVRC2012_val_00008555.JPEG",
    "wnid": "n02006656",
    "true_label": "spoonbill",
    "predicted_index": 129,
    "predicted_label": "spoonbill",
    "correct": true
  },
  {
    "image": "ILSVRC2012_val_00008978.JPEG",
    "wnid": "n02006656",
    "true_label": "spoonbill",
    "predicted_index": 129,
    "predicted_label": "spoonbill",
    "correct": true
  },
  {
    "image": "ILSVRC2012_val_00010002.JPEG",
    "wnid": "n02006656",
    "true_label": "spoonbill",
    "predicted_index": 129,
    "predicted_label": "spoonbill",
    "correct": true
  },
  {
    "image": "ILSVRC2012_val_00012618.JPEG",
    "wnid": "n02006656",
    "true_label": "spoonbill",
    "predicted_index": 129,
    "predicted_label": "spoonbill",
    "correct": true
  },
  {
    "image": "ILSVRC2012_val_00013110.JPEG",
    "wnid": "n02006656",
    "true_label": "spoonbill",
    "predicted_index": 129,
    "predicted_label": "spoonbill",
    "correct": true
  },
  {
    "image": "ILSVRC2012_val_00013256.JPEG",
    "wnid": "n02006656",
    "true_label": "spoonbill",
    "predicted_index": 129,
    "predicted_label": "spoonbill",
    "correct": true
  },
  {
    "image": "ILSVRC2012_val_00013457.JPEG",
    "wnid": "n02006656",
    "true_label": "spoonbill",
    "predicted_index": 129,
    "predicted_label": "spoonbill",
    "correct": true
  },
  {
    "image": "ILSVRC2012_val_00014266.JPEG",
    "wnid": "n02006656",
    "true_label": "spoonbill",
    "predicted_index": 129,
    "predicted_label": "spoonbill",
    "correct": true
  },
  {
    "image": "ILSVRC2012_val_00015505.JPEG",
    "wnid": "n02006656",
    "true_label": "spoonbill",
    "predicted_index": 129,
    "predicted_label": "spoonbill",
    "correct": true
  },
  {
    "image": "ILSVRC2012_val_00017069.JPEG",
    "wnid": "n02006656",
    "true_label": "spoonbill",
    "predicted_index": 129,
    "predicted_label": "spoonbill",
    "correct": true
  },
  {
    "image": "ILSVRC2012_val_00017690.JPEG",
    "wnid": "n02006656",
    "true_label": "spoonbill",
    "predicted_index": 129,
    "predicted_label": "spoonbill",
    "correct": true
  },
  {
    "image": "ILSVRC2012_val_00018192.JPEG",
    "wnid": "n02006656",
    "true_label": "spoonbill",
    "predicted_index": 129,
    "predicted_label": "spoonbill",
    "correct": true
  },
  {
    "image": "ILSVRC2012_val_00018489.JPEG",
    "wnid": "n02006656",
    "true_label": "spoonbill",
    "predicted_index": 129,
    "predicted_label": "spoonbill",
    "correct": true
  },
  {
    "image": "ILSVRC2012_val_00019210.JPEG",
    "wnid": "n02006656",
    "true_label": "spoonbill",
    "predicted_index": 129,
    "predicted_label": "spoonbill",
    "correct": true
  },
  {
    "image": "ILSVRC2012_val_00020933.JPEG",
    "wnid": "n02006656",
    "true_label": "spoonbill",
    "predicted_index": 129,
    "predicted_label": "spoonbill",
    "correct": true
  },
  {
    "image": "ILSVRC2012_val_00021933.JPEG",
    "wnid": "n02006656",
    "true_label": "spoonbill",
    "predicted_index": 129,
    "predicted_label": "spoonbill",
    "correct": true
  },
  {
    "image": "ILSVRC2012_val_00022418.JPEG",
    "wnid": "n02006656",
    "true_label": "spoonbill",
    "predicted_index": 129,
    "predicted_label": "spoonbill",
    "correct": true
  },
  {
    "image": "ILSVRC2012_val_00025075.JPEG",
    "wnid": "n02006656",
    "true_label": "spoonbill",
    "predicted_index": 129,
    "predicted_label": "spoonbill",
    "correct": true
  },
  {
    "image": "ILSVRC2012_val_00025126.JPEG",
    "wnid": "n02006656",
    "true_label": "spoonbill",
    "predicted_index": 129,
    "predicted_label": "spoonbill",
    "correct": true
  },
  {
    "image": "ILSVRC2012_val_00027667.JPEG",
    "wnid": "n02006656",
    "true_label": "spoonbill",
    "predicted_index": 129,
    "predicted_label": "spoonbill",
    "correct": true
  },
  {
    "image": "ILSVRC2012_val_00027676.JPEG",
    "wnid": "n02006656",
    "true_label": "spoonbill",
    "predicted_index": 129,
    "predicted_label": "spoonbill",
    "correct": true
  },
  {
    "image": "ILSVRC2012_val_00028586.JPEG",
    "wnid": "n02006656",
    "true_label": "spoonbill",
    "predicted_index": 129,
    "predicted_label": "spoonbill",
    "correct": true
  },
  {
    "image": "ILSVRC2012_val_00029168.JPEG",
    "wnid": "n02006656",
    "true_label": "spoonbill",
    "predicted_index": 129,
    "predicted_label": "spoonbill",
    "correct": true
  },
  {
    "image": "ILSVRC2012_val_00029736.JPEG",
    "wnid": "n02006656",
    "true_label": "spoonbill",
    "predicted_index": 129,
    "predicted_label": "spoonbill",
    "correct": true
  },
  {
    "image": "ILSVRC2012_val_00032335.JPEG",
    "wnid": "n02006656",
    "true_label": "spoonbill",
    "predicted_index": 129,
    "predicted_label": "spoonbill",
    "correct": true
  },
  {
    "image": "ILSVRC2012_val_00032470.JPEG",
    "wnid": "n02006656",
    "true_label": "spoonbill",
    "predicted_index": 129,
    "predicted_label": "spoonbill",
    "correct": true
  },
  {
    "image": "ILSVRC2012_val_00035605.JPEG",
    "wnid": "n02006656",
    "true_label": "spoonbill",
    "predicted_index": 129,
    "predicted_label": "spoonbill",
    "correct": true
  },
  {
    "image": "ILSVRC2012_val_00036074.JPEG",
    "wnid": "n02006656",
    "true_label": "spoonbill",
    "predicted_index": 129,
    "predicted_label": "spoonbill",
    "correct": true
  },
  {
    "image": "ILSVRC2012_val_00037552.JPEG",
    "wnid": "n02006656",
    "true_label": "spoonbill",
    "predicted_index": 129,
    "predicted_label": "spoonbill",
    "correct": true
  },
  {
    "image": "ILSVRC2012_val_00039784.JPEG",
    "wnid": "n02006656",
    "true_label": "spoonbill",
    "predicted_index": 129,
    "predicted_label": "spoonbill",
    "correct": true
  },
  {
    "image": "ILSVRC2012_val_00040455.JPEG",
    "wnid": "n02006656",
    "true_label": "spoonbill",
    "predicted_index": 129,
    "predicted_label": "spoonbill",
    "correct": true
  },
  {
    "image": "ILSVRC2012_val_00042758.JPEG",
    "wnid": "n02006656",
    "true_label": "spoonbill",
    "predicted_index": 129,
    "predicted_label": "spoonbill",
    "correct": true
  },
  {
    "image": "ILSVRC2012_val_00043081.JPEG",
    "wnid": "n02006656",
    "true_label": "spoonbill",
    "predicted_index": 129,
    "predicted_label": "spoonbill",
    "correct": true
  },
  {
    "image": "ILSVRC2012_val_00044522.JPEG",
    "wnid": "n02006656",
    "true_label": "spoonbill",
    "predicted_index": 129,
    "predicted_label": "spoonbill",
    "correct": true
  },
  {
    "image": "ILSVRC2012_val_00046732.JPEG",
    "wnid": "n02006656",
    "true_label": "spoonbill",
    "predicted_index": 129,
    "predicted_label": "spoonbill",
    "correct": true
  },
  {
    "image": "ILSVRC2012_val_00048553.JPEG",
    "wnid": "n02006656",
    "true_label": "spoonbill",
    "predicted_index": 129,
    "predicted_label": "spoonbill",
    "correct": true
  },
  {
    "image": "ILSVRC2012_val_00048666.JPEG",
    "wnid": "n02006656",
    "true_label": "spoonbill",
    "predicted_index": 129,
    "predicted_label": "spoonbill",
    "correct": true
  },
  {
    "image": "ILSVRC2012_val_00049077.JPEG",
    "wnid": "n02006656",
    "true_label": "spoonbill",
    "predicted_index": 129,
    "predicted_label": "spoonbill",
    "correct": true
  },
  {
    "image": "ILSVRC2012_val_00001268.JPEG",
    "wnid": "n01944390",
    "true_label": "snail",
    "predicted_index": 113,
    "predicted_label": "snail",
    "correct": true
  },
  {
    "image": "ILSVRC2012_val_00001959.JPEG",
    "wnid": "n01944390",
    "true_label": "snail",
    "predicted_index": 113,
    "predicted_label": "snail",
    "correct": true
  },
  {
    "image": "ILSVRC2012_val_00002602.JPEG",
    "wnid": "n01944390",
    "true_label": "snail",
    "predicted_index": 113,
    "predicted_label": "snail",
    "correct": true
  },
  {
    "image": "ILSVRC2012_val_00002763.JPEG",
    "wnid": "n01944390",
    "true_label": "snail",
    "predicted_index": 113,
    "predicted_label": "snail",
    "correct": true
  },
  {
    "image": "ILSVRC2012_val_00003604.JPEG",
    "wnid": "n01944390",
    "true_label": "snail",
    "predicted_index": 113,
    "predicted_label": "snail",
    "correct": true
  },
  {
    "image": "ILSVRC2012_val_00003625.JPEG",
    "wnid": "n01944390",
    "true_label": "snail",
    "predicted_index": 79,
    "predicted_label": "centipede",
    "correct": false
  },
  {
    "image": "ILSVRC2012_val_00006860.JPEG",
    "wnid": "n01944390",
    "true_label": "snail",
    "predicted_index": 114,
    "predicted_label": "slug",
    "correct": false
  },
  {
    "image": "ILSVRC2012_val_00007377.JPEG",
    "wnid": "n01944390",
    "true_label": "snail",
    "predicted_index": 988,
    "predicted_label": "acorn",
    "correct": false
  },
  {
    "image": "ILSVRC2012_val_00007479.JPEG",
    "wnid": "n01944390",
    "true_label": "snail",
    "predicted_index": 113,
    "predicted_label": "snail",
    "correct": true
  },
  {
    "image": "ILSVRC2012_val_00008002.JPEG",
    "wnid": "n01944390",
    "true_label": "snail",
    "predicted_index": 113,
    "predicted_label": "snail",
    "correct": true
  },
  {
    "image": "ILSVRC2012_val_00008747.JPEG",
    "wnid": "n01944390",
    "true_label": "snail",
    "predicted_index": 115,
    "predicted_label": "sea slug",
    "correct": false
  },
  {
    "image": "ILSVRC2012_val_00008789.JPEG",
    "wnid": "n01944390",
    "true_label": "snail",
    "predicted_index": 113,
    "predicted_label": "snail",
    "correct": true
  },
  {
    "image": "ILSVRC2012_val_00009202.JPEG",
    "wnid": "n01944390",
    "true_label": "snail",
    "predicted_index": 611,
    "predicted_label": "jigsaw puzzle",
    "correct": false
  },
  {
    "image": "ILSVRC2012_val_00009654.JPEG",
    "wnid": "n01944390",
    "true_label": "snail",
    "predicted_index": 113,
    "predicted_label": "snail",
    "correct": true
  },
  {
    "image": "ILSVRC2012_val_00010312.JPEG",
    "wnid": "n01944390",
    "true_label": "snail",
    "predicted_index": 113,
    "predicted_label": "snail",
    "correct": true
  },
  {
    "image": "ILSVRC2012_val_00010996.JPEG",
    "wnid": "n01944390",
    "true_label": "snail",
    "predicted_index": 113,
    "predicted_label": "snail",
    "correct": true
  },
  {
    "image": "ILSVRC2012_val_00012117.JPEG",
    "wnid": "n01944390",
    "true_label": "snail",
    "predicted_index": 113,
    "predicted_label": "snail",
    "correct": true
  },
  {
    "image": "ILSVRC2012_val_00012418.JPEG",
    "wnid": "n01944390",
    "true_label": "snail",
    "predicted_index": 113,
    "predicted_label": "snail",
    "correct": true
  },
  {
    "image": "ILSVRC2012_val_00013379.JPEG",
    "wnid": "n01944390",
    "true_label": "snail",
    "predicted_index": 116,
    "predicted_label": "chiton",
    "correct": false
  },
  {
    "image": "ILSVRC2012_val_00013503.JPEG",
    "wnid": "n01944390",
    "true_label": "snail",
    "predicted_index": 113,
    "predicted_label": "snail",
    "correct": true
  },
  {
    "image": "ILSVRC2012_val_00017431.JPEG",
    "wnid": "n01944390",
    "true_label": "snail",
    "predicted_index": 113,
    "predicted_label": "snail",
    "correct": true
  },
  {
    "image": "ILSVRC2012_val_00018951.JPEG",
    "wnid": "n01944390",
    "true_label": "snail",
    "predicted_index": 113,
    "predicted_label": "snail",
    "correct": true
  },
  {
    "image": "ILSVRC2012_val_00019782.JPEG",
    "wnid": "n01944390",
    "true_label": "snail",
    "predicted_index": 73,
    "predicted_label": "barn spider",
    "correct": false
  },
  {
    "image": "ILSVRC2012_val_00019895.JPEG",
    "wnid": "n01944390",
    "true_label": "snail",
    "predicted_index": 113,
    "predicted_label": "snail",
    "correct": true
  },
  {
    "image": "ILSVRC2012_val_00022381.JPEG",
    "wnid": "n01944390",
    "true_label": "snail",
    "predicted_index": 113,
    "predicted_label": "snail",
    "correct": true
  },
  {
    "image": "ILSVRC2012_val_00022758.JPEG",
    "wnid": "n01944390",
    "true_label": "snail",
    "predicted_index": 113,
    "predicted_label": "snail",
    "correct": true
  },
  {
    "image": "ILSVRC2012_val_00023206.JPEG",
    "wnid": "n01944390",
    "true_label": "snail",
    "predicted_index": 125,
    "predicted_label": "hermit crab",
    "correct": false
  },
  {
    "image": "ILSVRC2012_val_00023958.JPEG",
    "wnid": "n01944390",
    "true_label": "snail",
    "predicted_index": 113,
    "predicted_label": "snail",
    "correct": true
  },
  {
    "image": "ILSVRC2012_val_00024410.JPEG",
    "wnid": "n01944390",
    "true_label": "snail",
    "predicted_index": 113,
    "predicted_label": "snail",
    "correct": true
  },
  {
    "image": "ILSVRC2012_val_00025411.JPEG",
    "wnid": "n01944390",
    "true_label": "snail",
    "predicted_index": 113,
    "predicted_label": "snail",
    "correct": true
  },
  {
    "image": "ILSVRC2012_val_00025566.JPEG",
    "wnid": "n01944390",
    "true_label": "snail",
    "predicted_index": 113,
    "predicted_label": "snail",
    "correct": true
  },
  {
    "image": "ILSVRC2012_val_00025722.JPEG",
    "wnid": "n01944390",
    "true_label": "snail",
    "predicted_index": 113,
    "predicted_label": "snail",
    "correct": true
  },
  {
    "image": "ILSVRC2012_val_00025725.JPEG",
    "wnid": "n01944390",
    "true_label": "snail",
    "predicted_index": 113,
    "predicted_label": "snail",
    "correct": true
  },
  {
    "image": "ILSVRC2012_val_00025840.JPEG",
    "wnid": "n01944390",
    "true_label": "snail",
    "predicted_index": 113,
    "predicted_label": "snail",
    "correct": true
  },
  {
    "image": "ILSVRC2012_val_00030012.JPEG",
    "wnid": "n01944390",
    "true_label": "snail",
    "predicted_index": 113,
    "predicted_label": "snail",
    "correct": true
  },
  {
    "image": "ILSVRC2012_val_00030395.JPEG",
    "wnid": "n01944390",
    "true_label": "snail",
    "predicted_index": 113,
    "predicted_label": "snail",
    "correct": true
  },
  {
    "image": "ILSVRC2012_val_00034957.JPEG",
    "wnid": "n01944390",
    "true_label": "snail",
    "predicted_index": 637,
    "predicted_label": "mailbox",
    "correct": false
  },
  {
    "image": "ILSVRC2012_val_00036200.JPEG",
    "wnid": "n01944390",
    "true_label": "snail",
    "predicted_index": 113,
    "predicted_label": "snail",
    "correct": true
  },
  {
    "image": "ILSVRC2012_val_00036494.JPEG",
    "wnid": "n01944390",
    "true_label": "snail",
    "predicted_index": 113,
    "predicted_label": "snail",
    "correct": true
  },
  {
    "image": "ILSVRC2012_val_00038059.JPEG",
    "wnid": "n01944390",
    "true_label": "snail",
    "predicted_index": 113,
    "predicted_label": "snail",
    "correct": true
  },
  {
    "image": "ILSVRC2012_val_00039434.JPEG",
    "wnid": "n01944390",
    "true_label": "snail",
    "predicted_index": 113,
    "predicted_label": "snail",
    "correct": true
  },
  {
    "image": "ILSVRC2012_val_00040123.JPEG",
    "wnid": "n01944390",
    "true_label": "snail",
    "predicted_index": 113,
    "predicted_label": "snail",
    "correct": true
  },
  {
    "image": "ILSVRC2012_val_00040504.JPEG",
    "wnid": "n01944390",
    "true_label": "snail",
    "predicted_index": 65,
    "predicted_label": "sea snake",
    "correct": false
  },
  {
    "image": "ILSVRC2012_val_00045031.JPEG",
    "wnid": "n01944390",
    "true_label": "snail",
    "predicted_index": 113,
    "predicted_label": "snail",
    "correct": true
  },
  {
    "image": "ILSVRC2012_val_00045945.JPEG",
    "wnid": "n01944390",
    "true_label": "snail",
    "predicted_index": 113,
    "predicted_label": "snail",
    "correct": true
  },
  {
    "image": "ILSVRC2012_val_00046248.JPEG",
    "wnid": "n01944390",
    "true_label": "snail",
    "predicted_index": 113,
    "predicted_label": "snail",
    "correct": true
  },
  {
    "image": "ILSVRC2012_val_00046551.JPEG",
    "wnid": "n01944390",
    "true_label": "snail",
    "predicted_index": 113,
    "predicted_label": "snail",
    "correct": true
  },
  {
    "image": "ILSVRC2012_val_00046883.JPEG",
    "wnid": "n01944390",
    "true_label": "snail",
    "predicted_index": 113,
    "predicted_label": "snail",
    "correct": true
  },
  {
    "image": "ILSVRC2012_val_00047412.JPEG",
    "wnid": "n01944390",
    "true_label": "snail",
    "predicted_index": 910,
    "predicted_label": "wooden spoon",
    "correct": false
  },
  {
    "image": "ILSVRC2012_val_00049410.JPEG",
    "wnid": "n01944390",
    "true_label": "snail",
    "predicted_index": 113,
    "predicted_label": "snail",
    "correct": true
  },
  {
    "image": "ILSVRC2012_val_00001146.JPEG",
    "wnid": "n01806143",
    "true_label": "peacock",
    "predicted_index": 134,
    "predicted_label": "crane bird",
    "correct": false
  },
  {
    "image": "ILSVRC2012_val_00002177.JPEG",
    "wnid": "n01806143",
    "true_label": "peacock",
    "predicted_index": 89,
    "predicted_label": "sulphur-crested cockatoo",
    "correct": false
  },
  {
    "image": "ILSVRC2012_val_00002383.JPEG",
    "wnid": "n01806143",
    "true_label": "peacock",
    "predicted_index": 84,
    "predicted_label": "peacock",
    "correct": true
  },
  {
    "image": "ILSVRC2012_val_00003588.JPEG",
    "wnid": "n01806143",
    "true_label": "peacock",
    "predicted_index": 84,
    "predicted_label": "peacock",
    "correct": true
  },
  {
    "image": "ILSVRC2012_val_00005599.JPEG",
    "wnid": "n01806143",
    "true_label": "peacock",
    "predicted_index": 84,
    "predicted_label": "peacock",
    "correct": true
  },
  {
    "image": "ILSVRC2012_val_00005751.JPEG",
    "wnid": "n01806143",
    "true_label": "peacock",
    "predicted_index": 84,
    "predicted_label": "peacock",
    "correct": true
  },
  {
    "image": "ILSVRC2012_val_00008186.JPEG",
    "wnid": "n01806143",
    "true_label": "peacock",
    "predicted_index": 84,
    "predicted_label": "peacock",
    "correct": true
  },
  {
    "image": "ILSVRC2012_val_00008245.JPEG",
    "wnid": "n01806143",
    "true_label": "peacock",
    "predicted_index": 92,
    "predicted_label": "bee eater",
    "correct": false
  },
  {
    "image": "ILSVRC2012_val_00011943.JPEG",
    "wnid": "n01806143",
    "true_label": "peacock",
    "predicted_index": 84,
    "predicted_label": "peacock",
    "correct": true
  },
  {
    "image": "ILSVRC2012_val_00012122.JPEG",
    "wnid": "n01806143",
    "true_label": "peacock",
    "predicted_index": 84,
    "predicted_label": "peacock",
    "correct": true
  },
  {
    "image": "ILSVRC2012_val_00013378.JPEG",
    "wnid": "n01806143",
    "true_label": "peacock",
    "predicted_index": 84,
    "predicted_label": "peacock",
    "correct": true
  },
  {
    "image": "ILSVRC2012_val_00014023.JPEG",
    "wnid": "n01806143",
    "true_label": "peacock",
    "predicted_index": 84,
    "predicted_label": "peacock",
    "correct": true
  },
  {
    "image": "ILSVRC2012_val_00014890.JPEG",
    "wnid": "n01806143",
    "true_label": "peacock",
    "predicted_index": 342,
    "predicted_label": "wild boar",
    "correct": false
  },
  {
    "image": "ILSVRC2012_val_00017068.JPEG",
    "wnid": "n01806143",
    "true_label": "peacock",
    "predicted_index": 84,
    "predicted_label": "peacock",
    "correct": true
  },
  {
    "image": "ILSVRC2012_val_00020915.JPEG",
    "wnid": "n01806143",
    "true_label": "peacock",
    "predicted_index": 84,
    "predicted_label": "peacock",
    "correct": true
  },
  {
    "image": "ILSVRC2012_val_00021345.JPEG",
    "wnid": "n01806143",
    "true_label": "peacock",
    "predicted_index": 84,
    "predicted_label": "peacock",
    "correct": true
  },
  {
    "image": "ILSVRC2012_val_00022422.JPEG",
    "wnid": "n01806143",
    "true_label": "peacock",
    "predicted_index": 84,
    "predicted_label": "peacock",
    "correct": true
  },
  {
    "image": "ILSVRC2012_val_00022767.JPEG",
    "wnid": "n01806143",
    "true_label": "peacock",
    "predicted_index": 84,
    "predicted_label": "peacock",
    "correct": true
  },
  {
    "image": "ILSVRC2012_val_00023973.JPEG",
    "wnid": "n01806143",
    "true_label": "peacock",
    "predicted_index": 84,
    "predicted_label": "peacock",
    "correct": true
  },
  {
    "image": "ILSVRC2012_val_00024040.JPEG",
    "wnid": "n01806143",
    "true_label": "peacock",
    "predicted_index": 84,
    "predicted_label": "peacock",
    "correct": true
  },
  {
    "image": "ILSVRC2012_val_00024438.JPEG",
    "wnid": "n01806143",
    "true_label": "peacock",
    "predicted_index": 84,
    "predicted_label": "peacock",
    "correct": true
  },
  {
    "image": "ILSVRC2012_val_00025543.JPEG",
    "wnid": "n01806143",
    "true_label": "peacock",
    "predicted_index": 664,
    "predicted_label": "monitor",
    "correct": false
  },
  {
    "image": "ILSVRC2012_val_00027047.JPEG",
    "wnid": "n01806143",
    "true_label": "peacock",
    "predicted_index": 84,
    "predicted_label": "peacock",
    "correct": true
  },
  {
    "image": "ILSVRC2012_val_00028159.JPEG",
    "wnid": "n01806143",
    "true_label": "peacock",
    "predicted_index": 84,
    "predicted_label": "peacock",
    "correct": true
  },
  {
    "image": "ILSVRC2012_val_00028208.JPEG",
    "wnid": "n01806143",
    "true_label": "peacock",
    "predicted_index": 84,
    "predicted_label": "peacock",
    "correct": true
  },
  {
    "image": "ILSVRC2012_val_00028548.JPEG",
    "wnid": "n01806143",
    "true_label": "peacock",
    "predicted_index": 84,
    "predicted_label": "peacock",
    "correct": true
  },
  {
    "image": "ILSVRC2012_val_00028656.JPEG",
    "wnid": "n01806143",
    "true_label": "peacock",
    "predicted_index": 14,
    "predicted_label": "indigo bunting",
    "correct": false
  },
  {
    "image": "ILSVRC2012_val_00030028.JPEG",
    "wnid": "n01806143",
    "true_label": "peacock",
    "predicted_index": 84,
    "predicted_label": "peacock",
    "correct": true
  },
  {
    "image": "ILSVRC2012_val_00032072.JPEG",
    "wnid": "n01806143",
    "true_label": "peacock",
    "predicted_index": 84,
    "predicted_label": "peacock",
    "correct": true
  },
  {
    "image": "ILSVRC2012_val_00033059.JPEG",
    "wnid": "n01806143",
    "true_label": "peacock",
    "predicted_index": 84,
    "predicted_label": "peacock",
    "correct": true
  },
  {
    "image": "ILSVRC2012_val_00033147.JPEG",
    "wnid": "n01806143",
    "true_label": "peacock",
    "predicted_index": 84,
    "predicted_label": "peacock",
    "correct": true
  },
  {
    "image": "ILSVRC2012_val_00035287.JPEG",
    "wnid": "n01806143",
    "true_label": "peacock",
    "predicted_index": 84,
    "predicted_label": "peacock",
    "correct": true
  },
  {
    "image": "ILSVRC2012_val_00035974.JPEG",
    "wnid": "n01806143",
    "true_label": "peacock",
    "predicted_index": 84,
    "predicted_label": "peacock",
    "correct": true
  },
  {
    "image": "ILSVRC2012_val_00037524.JPEG",
    "wnid": "n01806143",
    "true_label": "peacock",
    "predicted_index": 84,
    "predicted_label": "peacock",
    "correct": true
  },
  {
    "image": "ILSVRC2012_val_00037892.JPEG",
    "wnid": "n01806143",
    "true_label": "peacock",
    "predicted_index": 84,
    "predicted_label": "peacock",
    "correct": true
  },
  {
    "image": "ILSVRC2012_val_00038324.JPEG",
    "wnid": "n01806143",
    "true_label": "peacock",
    "predicted_index": 839,
    "predicted_label": "suspension bridge",
    "correct": false
  },
  {
    "image": "ILSVRC2012_val_00039299.JPEG",
    "wnid": "n01806143",
    "true_label": "peacock",
    "predicted_index": 84,
    "predicted_label": "peacock",
    "correct": true
  },
  {
    "image": "ILSVRC2012_val_00040701.JPEG",
    "wnid": "n01806143",
    "true_label": "peacock",
    "predicted_index": 84,
    "predicted_label": "peacock",
    "correct": true
  },
  {
    "image": "ILSVRC2012_val_00040811.JPEG",
    "wnid": "n01806143",
    "true_label": "peacock",
    "predicted_index": 753,
    "predicted_label": "radiator",
    "correct": false
  },
  {
    "image": "ILSVRC2012_val_00041845.JPEG",
    "wnid": "n01806143",
    "true_label": "peacock",
    "predicted_index": 84,
    "predicted_label": "peacock",
    "correct": true
  },
  {
    "image": "ILSVRC2012_val_00041983.JPEG",
    "wnid": "n01806143",
    "true_label": "peacock",
    "predicted_index": 84,
    "predicted_label": "peacock",
    "correct": true
  },
  {
    "image": "ILSVRC2012_val_00042998.JPEG",
    "wnid": "n01806143",
    "true_label": "peacock",
    "predicted_index": 84,
    "predicted_label": "peacock",
    "correct": true
  },
  {
    "image": "ILSVRC2012_val_00043483.JPEG",
    "wnid": "n01806143",
    "true_label": "peacock",
    "predicted_index": 84,
    "predicted_label": "peacock",
    "correct": true
  },
  {
    "image": "ILSVRC2012_val_00043808.JPEG",
    "wnid": "n01806143",
    "true_label": "peacock",
    "predicted_index": 84,
    "predicted_label": "peacock",
    "correct": true
  },
  {
    "image": "ILSVRC2012_val_00044216.JPEG",
    "wnid": "n01806143",
    "true_label": "peacock",
    "predicted_index": 84,
    "predicted_label": "peacock",
    "correct": true
  },
  {
    "image": "ILSVRC2012_val_00046380.JPEG",
    "wnid": "n01806143",
    "true_label": "peacock",
    "predicted_index": 84,
    "predicted_label": "peacock",
    "correct": true
  },
  {
    "image": "ILSVRC2012_val_00046958.JPEG",
    "wnid": "n01806143",
    "true_label": "peacock",
    "predicted_index": 136,
    "predicted_label": "European gallinule",
    "correct": false
  },
  {
    "image": "ILSVRC2012_val_00048700.JPEG",
    "wnid": "n01806143",
    "true_label": "peacock",
    "predicted_index": 84,
    "predicted_label": "peacock",
    "correct": true
  },
  {
    "image": "ILSVRC2012_val_00049584.JPEG",
    "wnid": "n01806143",
    "true_label": "peacock",
    "predicted_index": 84,
    "predicted_label": "peacock",
    "correct": true
  },
  {
    "image": "ILSVRC2012_val_00049665.JPEG",
    "wnid": "n01806143",
    "true_label": "peacock",
    "predicted_index": 133,
    "predicted_label": "bittern",
    "correct": false
  },
  {
    "image": "ILSVRC2012_val_00002974.JPEG",
    "wnid": "n01833805",
    "true_label": "hummingbird",
    "predicted_index": 94,
    "predicted_label": "hummingbird",
    "correct": true
  },
  {
    "image": "ILSVRC2012_val_00003064.JPEG",
    "wnid": "n01833805",
    "true_label": "hummingbird",
    "predicted_index": 94,
    "predicted_label": "hummingbird",
    "correct": true
  },
  {
    "image": "ILSVRC2012_val_00003259.JPEG",
    "wnid": "n01833805",
    "true_label": "hummingbird",
    "predicted_index": 94,
    "predicted_label": "hummingbird",
    "correct": true
  },
  {
    "image": "ILSVRC2012_val_00004234.JPEG",
    "wnid": "n01833805",
    "true_label": "hummingbird",
    "predicted_index": 94,
    "predicted_label": "hummingbird",
    "correct": true
  },
  {
    "image": "ILSVRC2012_val_00005150.JPEG",
    "wnid": "n01833805",
    "true_label": "hummingbird",
    "predicted_index": 94,
    "predicted_label": "hummingbird",
    "correct": true
  },
  {
    "image": "ILSVRC2012_val_00005779.JPEG",
    "wnid": "n01833805",
    "true_label": "hummingbird",
    "predicted_index": 94,
    "predicted_label": "hummingbird",
    "correct": true
  },
  {
    "image": "ILSVRC2012_val_00005873.JPEG",
    "wnid": "n01833805",
    "true_label": "hummingbird",
    "predicted_index": 94,
    "predicted_label": "hummingbird",
    "correct": true
  },
  {
    "image": "ILSVRC2012_val_00007390.JPEG",
    "wnid": "n01833805",
    "true_label": "hummingbird",
    "predicted_index": 94,
    "predicted_label": "hummingbird",
    "correct": true
  },
  {
    "image": "ILSVRC2012_val_00010570.JPEG",
    "wnid": "n01833805",
    "true_label": "hummingbird",
    "predicted_index": 94,
    "predicted_label": "hummingbird",
    "correct": true
  },
  {
    "image": "ILSVRC2012_val_00011894.JPEG",
    "wnid": "n01833805",
    "true_label": "hummingbird",
    "predicted_index": 94,
    "predicted_label": "hummingbird",
    "correct": true
  },
  {
    "image": "ILSVRC2012_val_00013085.JPEG",
    "wnid": "n01833805",
    "true_label": "hummingbird",
    "predicted_index": 94,
    "predicted_label": "hummingbird",
    "correct": true
  },
  {
    "image": "ILSVRC2012_val_00013434.JPEG",
    "wnid": "n01833805",
    "true_label": "hummingbird",
    "predicted_index": 94,
    "predicted_label": "hummingbird",
    "correct": true
  },
  {
    "image": "ILSVRC2012_val_00013610.JPEG",
    "wnid": "n01833805",
    "true_label": "hummingbird",
    "predicted_index": 95,
    "predicted_label": "jacamar",
    "correct": false
  },
  {
    "image": "ILSVRC2012_val_00015665.JPEG",
    "wnid": "n01833805",
    "true_label": "hummingbird",
    "predicted_index": 94,
    "predicted_label": "hummingbird",
    "correct": true
  },
  {
    "image": "ILSVRC2012_val_00015854.JPEG",
    "wnid": "n01833805",
    "true_label": "hummingbird",
    "predicted_index": 94,
    "predicted_label": "hummingbird",
    "correct": true
  },
  {
    "image": "ILSVRC2012_val_00016325.JPEG",
    "wnid": "n01833805",
    "true_label": "hummingbird",
    "predicted_index": 94,
    "predicted_label": "hummingbird",
    "correct": true
  },
  {
    "image": "ILSVRC2012_val_00016623.JPEG",
    "wnid": "n01833805",
    "true_label": "hummingbird",
    "predicted_index": 94,
    "predicted_label": "hummingbird",
    "correct": true
  },
  {
    "image": "ILSVRC2012_val_00016746.JPEG",
    "wnid": "n01833805",
    "true_label": "hummingbird",
    "predicted_index": 94,
    "predicted_label": "hummingbird",
    "correct": true
  },
  {
    "image": "ILSVRC2012_val_00017251.JPEG",
    "wnid": "n01833805",
    "true_label": "hummingbird",
    "predicted_index": 94,
    "predicted_label": "hummingbird",
    "correct": true
  },
  {
    "image": "ILSVRC2012_val_00020443.JPEG",
    "wnid": "n01833805",
    "true_label": "hummingbird",
    "predicted_index": 94,
    "predicted_label": "hummingbird",
    "correct": true
  },
  {
    "image": "ILSVRC2012_val_00021281.JPEG",
    "wnid": "n01833805",
    "true_label": "hummingbird",
    "predicted_index": 94,
    "predicted_label": "hummingbird",
    "correct": true
  },
  {
    "image": "ILSVRC2012_val_00023796.JPEG",
    "wnid": "n01833805",
    "true_label": "hummingbird",
    "predicted_index": 94,
    "predicted_label": "hummingbird",
    "correct": true
  },
  {
    "image": "ILSVRC2012_val_00024336.JPEG",
    "wnid": "n01833805",
    "true_label": "hummingbird",
    "predicted_index": 94,
    "predicted_label": "hummingbird",
    "correct": true
  },
  {
    "image": "ILSVRC2012_val_00025449.JPEG",
    "wnid": "n01833805",
    "true_label": "hummingbird",
    "predicted_index": 94,
    "predicted_label": "hummingbird",
    "correct": true
  },
  {
    "image": "ILSVRC2012_val_00025928.JPEG",
    "wnid": "n01833805",
    "true_label": "hummingbird",
    "predicted_index": 94,
    "predicted_label": "hummingbird",
    "correct": true
  },
  {
    "image": "ILSVRC2012_val_00026090.JPEG",
    "wnid": "n01833805",
    "true_label": "hummingbird",
    "predicted_index": 94,
    "predicted_label": "hummingbird",
    "correct": true
  },
  {
    "image": "ILSVRC2012_val_00027986.JPEG",
    "wnid": "n01833805",
    "true_label": "hummingbird",
    "predicted_index": 94,
    "predicted_label": "hummingbird",
    "correct": true
  },
  {
    "image": "ILSVRC2012_val_00028801.JPEG",
    "wnid": "n01833805",
    "true_label": "hummingbird",
    "predicted_index": 94,
    "predicted_label": "hummingbird",
    "correct": true
  },
  {
    "image": "ILSVRC2012_val_00029356.JPEG",
    "wnid": "n01833805",
    "true_label": "hummingbird",
    "predicted_index": 94,
    "predicted_label": "hummingbird",
    "correct": true
  },
  {
    "image": "ILSVRC2012_val_00029571.JPEG",
    "wnid": "n01833805",
    "true_label": "hummingbird",
    "predicted_index": 94,
    "predicted_label": "hummingbird",
    "correct": true
  },
  {
    "image": "ILSVRC2012_val_00030278.JPEG",
    "wnid": "n01833805",
    "true_label": "hummingbird",
    "predicted_index": 94,
    "predicted_label": "hummingbird",
    "correct": true
  },
  {
    "image": "ILSVRC2012_val_00030431.JPEG",
    "wnid": "n01833805",
    "true_label": "hummingbird",
    "predicted_index": 94,
    "predicted_label": "hummingbird",
    "correct": true
  },
  {
    "image": "ILSVRC2012_val_00032159.JPEG",
    "wnid": "n01833805",
    "true_label": "hummingbird",
    "predicted_index": 94,
    "predicted_label": "hummingbird",
    "correct": true
  },
  {
    "image": "ILSVRC2012_val_00032985.JPEG",
    "wnid": "n01833805",
    "true_label": "hummingbird",
    "predicted_index": 94,
    "predicted_label": "hummingbird",
    "correct": true
  },
  {
    "image": "ILSVRC2012_val_00033186.JPEG",
    "wnid": "n01833805",
    "true_label": "hummingbird",
    "predicted_index": 15,
    "predicted_label": "robin",
    "correct": false
  },
  {
    "image": "ILSVRC2012_val_00033829.JPEG",
    "wnid": "n01833805",
    "true_label": "hummingbird",
    "predicted_index": 94,
    "predicted_label": "hummingbird",
    "correct": true
  },
  {
    "image": "ILSVRC2012_val_00035726.JPEG",
    "wnid": "n01833805",
    "true_label": "hummingbird",
    "predicted_index": 94,
    "predicted_label": "hummingbird",
    "correct": true
  },
  {
    "image": "ILSVRC2012_val_00037002.JPEG",
    "wnid": "n01833805",
    "true_label": "hummingbird",
    "predicted_index": 94,
    "predicted_label": "hummingbird",
    "correct": true
  },
  {
    "image": "ILSVRC2012_val_00037397.JPEG",
    "wnid": "n01833805",
    "true_label": "hummingbird",
    "predicted_index": 503,
    "predicted_label": "cocktail shaker",
    "correct": false
  },
  {
    "image": "ILSVRC2012_val_00037471.JPEG",
    "wnid": "n01833805",
    "true_label": "hummingbird",
    "predicted_index": 94,
    "predicted_label": "hummingbird",
    "correct": true
  },
  {
    "image": "ILSVRC2012_val_00038443.JPEG",
    "wnid": "n01833805",
    "true_label": "hummingbird",
    "predicted_index": 94,
    "predicted_label": "hummingbird",
    "correct": true
  },
  {
    "image": "ILSVRC2012_val_00038563.JPEG",
    "wnid": "n01833805",
    "true_label": "hummingbird",
    "predicted_index": 988,
    "predicted_label": "acorn",
    "correct": false
  },
  {
    "image": "ILSVRC2012_val_00041200.JPEG",
    "wnid": "n01833805",
    "true_label": "hummingbird",
    "predicted_index": 94,
    "predicted_label": "hummingbird",
    "correct": true
  },
  {
    "image": "ILSVRC2012_val_00041498.JPEG",
    "wnid": "n01833805",
    "true_label": "hummingbird",
    "predicted_index": 94,
    "predicted_label": "hummingbird",
    "correct": true
  },
  {
    "image": "ILSVRC2012_val_00043465.JPEG",
    "wnid": "n01833805",
    "true_label": "hummingbird",
    "predicted_index": 506,
    "predicted_label": "coil",
    "correct": false
  },
  {
    "image": "ILSVRC2012_val_00044011.JPEG",
    "wnid": "n01833805",
    "true_label": "hummingbird",
    "predicted_index": 94,
    "predicted_label": "hummingbird",
    "correct": true
  },
  {
    "image": "ILSVRC2012_val_00048347.JPEG",
    "wnid": "n01833805",
    "true_label": "hummingbird",
    "predicted_index": 94,
    "predicted_label": "hummingbird",
    "correct": true
  },
  {
    "image": "ILSVRC2012_val_00048749.JPEG",
    "wnid": "n01833805",
    "true_label": "hummingbird",
    "predicted_index": 94,
    "predicted_label": "hummingbird",
    "correct": true
  },
  {
    "image": "ILSVRC2012_val_00048838.JPEG",
    "wnid": "n01833805",
    "true_label": "hummingbird",
    "predicted_index": 94,
    "predicted_label": "hummingbird",
    "correct": true
  },
  {
    "image": "ILSVRC2012_val_00049966.JPEG",
    "wnid": "n01833805",
    "true_label": "hummingbird",
    "predicted_index": 94,
    "predicted_label": "hummingbird",
    "correct": true
  }
]}